Workbook

Sheet Assumptions
A1: US Tokenized Equity Market: TAM Sizing Model
A2: Assumptions & Market Segmentation
A4: US Equity Market Overview | F4: Source | G4: Link
A5: Total US listed companies (major exchanges) | B5: 4400 | F5: Source: World Federation of Exchanges, NYSE/NASDAQ listings data, 2025 | G5: https://www.sifma.org/resources/research/us-equity-markets-statistics/
A6: Total US equity market cap ($Bn) | B6: 58000 | F6: Source: SIFMA Capital Markets Fact Book, May 2025; S&P Global | G6: https://www.sifma.org/resources/research/fact-book/
A7: Total US equity ADV ($Bn) | B7: 550 | F7: Source: CBOE Global Markets monthly volume data, 2025 avg | G7: https://www.cboe.com/us/equities/market_statistics/
A9: ADV-Based Segmentation | F9: Source | G9: Link
B10: Low ADV | C10: Mid ADV | D10: High ADV | E10: Total / Check
A11: ADV threshold | B11: <$5M / day | C11: $5M - $50M / day | D11: >$50M / day
A12: Number of companies | B12: 2400 | C12: 1500 | D12: 500 | E12: =SUM(B12:D12) -> 4400 | F12: Source: Bernstein estimate; segmented from NYSE/NASDAQ ADV screens | G12: Bernstein estimate — derived from Bloomberg ADV screening
A13: Aggregate market cap ($Bn) | B13: 3000 | C13: 10000 | D13: 45000 | E13: =SUM(B13:D13) -> 58000 | F13: Source: Bernstein estimate; S&P Global Market Intelligence mkt cap data | G13: Bernstein estimate — derived from S&P Global Market Intelligence
A14: % of total market cap | B14: =B13/$E13 -> 0.051724138 | C14: =C13/$E13 -> 0.17241379 | D14: =D13/$E13 -> 0.77586207 | E14: =SUM(B14:D14) -> 1
A15: Avg market cap per company ($Bn) | B15: =B13/B12 -> 1.25 | C15: =C13/C12 -> 6.6666667 | D15: =D13/D12 -> 90
A17: Tokenization Penetration Assumptions (% of segment mkt cap)
A18: Rationale | B18: Early adopters: illiquid names benefit most from 24/7 trading, fractional access
A20: Year | B20: Low ADV Penetration | C20: Mid ADV Penetration | D20: High ADV Penetration | F20: Source / Rationale | G20: Link / Reference
A21: 2026 | B21: 0.001 | C21: 0 | D21: 0 | F21: DTCC Oct 2026 launch; Figure/Securitize early listings | G21: DTCC digital securities platform announcement
A22: 2027 | B22: 0.005 | C22: 0.002 | D22: 0 | F22: Regulatory clarity (CLARITY Act); 2-3 transfer agents live | G22: CLARITY Act — H.R. text (Congress.gov)
A23: 2028 | B23: 0.015 | C23: 0.005 | D23: 0.001 | F23: Broadening issuer adoption; mid-cap issuers begin migration | G23: Securitize — SEC-registered transfer agent
A24: 2029 | B24: 0.035 | C24: 0.012 | D24: 0.003 | F24: NYSE/Securitize/Computershare pipeline fills; ETF wrapper precedent | G24: NYSE / Securitize digital shares partnership
A25: 2030 | B25: 0.06 | C25: 0.025 | D25: 0.006 | F25: Institutional custody solutions mature; 24/7 settlement demand | G25: Computershare blockchain transfer agent filing
A26: 2031 | B26: 0.09 | C26: 0.04 | D26: 0.01 | F26: Large-cap pilot programs begin; major exchange integration | G26: Figure OPEN network — tokenized equity issuance
A27: 2032 | B27: 0.12 | C27: 0.06 | D27: 0.02 | F27: Cross-border interoperability; non-US investor access unlocked | G27: Robinhood EU — tokenized US stock trading launch
A28: 2033 | B28: 0.15 | C28: 0.08 | D28: 0.03 | F28: Collateral mobility use case drives high-ADV adoption | G28: Broadridge DLT repo / collateral platform
A29: 2034 | B29: 0.18 | C29: 0.1 | D29: 0.04 | F29: Full clearing/settlement migration for early-adopter segments | G29: BlackRock BUIDL tokenized fund (on-chain collateral precedent)
A30: 2035 | B30: 0.2 | C30: 0.12 | D30: 0.05 | F30: Terminal state; analogous to ~20% ETF penetration at 10-yr mark | G30: ETF penetration analogue — ICI Fact Book
A32: Market Cap Growth Assumptions
A33: Annual equity market cap growth rate | B33: 0.05 | C33: Applied uniformly across segments | F33: Source: Bernstein assumption; ~long-run nominal equity return | G33: Bernstein LT equity return assumption (nominal)

Sheet Projection
A1: US Tokenized Equity Market Cap Projection ($Bn)
B3: 2026 | C3: 2027 | D3: 2028 | E3: 2029 | F3: 2030 | G3: 2031 | H3: 2032 | I3: 2033 | J3: 2034 | K3: 2035
A4: SEGMENT MARKET CAP (GROWING AT EQUITY MKT GROWTH RATE)
A5: Low ADV segment market cap ($Bn) | B5: =Assumptions!B13 -> 3000 | C5: =B5*(1+Assumptions!B33) -> 3150 | D5: =C5*(1+Assumptions!B33) -> 3307.5 | E5: =D5*(1+Assumptions!B33) -> 3472.875 | F5: =E5*(1+Assumptions!B33) -> 3646.5188 | G5: =F5*(1+Assumptions!B33) -> 3828.8447 | H5: =G5*(1+Assumptions!B33) -> 4020.2869 | I5: =H5*(1+Assumptions!B33) -> 4221.3013 | J5: =I5*(1+Assumptions!B33) -> 4432.3663 | K5: =J5*(1+Assumptions!B33) -> 4653.9846
A6: Mid ADV segment market cap ($Bn) | B6: =Assumptions!C13 -> 10000 | C6: =B6*(1+Assumptions!B33) -> 10500 | D6: =C6*(1+Assumptions!B33) -> 11025 | E6: =D6*(1+Assumptions!B33) -> 11576.25 | F6: =E6*(1+Assumptions!B33) -> 12155.062 | G6: =F6*(1+Assumptions!B33) -> 12762.816 | H6: =G6*(1+Assumptions!B33) -> 13400.956 | I6: =H6*(1+Assumptions!B33) -> 14071.004 | J6: =I6*(1+Assumptions!B33) -> 14774.554 | K6: =J6*(1+Assumptions!B33) -> 15513.282
A7: High ADV segment market cap ($Bn) | B7: =Assumptions!D13 -> 45000 | C7: =B7*(1+Assumptions!B33) -> 47250 | D7: =C7*(1+Assumptions!B33) -> 49612.5 | E7: =D7*(1+Assumptions!B33) -> 52093.125 | F7: =E7*(1+Assumptions!B33) -> 54697.781 | G7: =F7*(1+Assumptions!B33) -> 57432.67 | H7: =G7*(1+Assumptions!B33) -> 60304.304 | I7: =H7*(1+Assumptions!B33) -> 63319.519 | J7: =I7*(1+Assumptions!B33) -> 66485.495 | K7: =J7*(1+Assumptions!B33) -> 69809.77
A8: Total US equity market cap ($Bn) | B8: =SUM(B5:B7) -> 58000 | C8: =SUM(C5:C7) -> 60900 | D8: =SUM(D5:D7) -> 63945 | E8: =SUM(E5:E7) -> 67142.25 | F8: =SUM(F5:F7) -> 70499.363 | G8: =SUM(G5:G7) -> 74024.331 | H8: =SUM(H5:H7) -> 77725.547 | I8: =SUM(I5:I7) -> 81611.825 | ... K8: =SUM(K5:K7) -> 89977.037
A10: TOKENIZATION PENETRATION RATES
A11: Low ADV penetration | B11: =Assumptions!B21 -> 0.001 | C11: =Assumptions!B22 -> 0.005 | D11: =Assumptions!B23 -> 0.015 | E11: =Assumptions!B24 -> 0.035 | F11: =Assumptions!B25 -> 0.06 | G11: =Assumptions!B26 -> 0.09 | H11: =Assumptions!B27 -> 0.12 | I11: =Assumptions!B28 -> 0.15 | J11: =Assumptions!B29 -> 0.18 | K11: =Assumptions!B30 -> 0.2
A12: Mid ADV penetration | B12: =Assumptions!C21 -> 0 | C12: =Assumptions!C22 -> 0.002 | D12: =Assumptions!C23 -> 0.005 | E12: =Assumptions!C24 -> 0.012 | F12: =Assumptions!C25 -> 0.025 | G12: =Assumptions!C26 -> 0.04 | H12: =Assumptions!C27 -> 0.06 | I12: =Assumptions!C28 -> 0.08 | J12: =Assumptions!C29 -> 0.1 | K12: =Assumptions!C30 -> 0.12
A13: High ADV penetration | B13: =Assumptions!D21 -> 0 | C13: =Assumptions!D22 -> 0 | D13: =Assumptions!D23 -> 0.001 | E13: =Assumptions!D24 -> 0.003 | F13: =Assumptions!D25 -> 0.006 | G13: =Assumptions!D26 -> 0.01 | H13: =Assumptions!D27 -> 0.02 | I13: =Assumptions!D28 -> 0.03 | J13: =Assumptions!D29 -> 0.04 | K13: =Assumptions!D30 -> 0.05
A15: TOKENIZED MARKET CAP BY SEGMENT ($Bn)
A16: Low ADV tokenized mkt cap ($Bn) | B16: =B5*B11 -> 3 | C16: =C5*C11 -> 15.75 | D16: =D5*D11 -> 49.6125 | E16: =E5*E11 -> 121.55063 | F16: =F5*F11 -> 218.79112 | G16: =G5*G11 -> 344.59602 | H16: =H5*H11 -> 482.43443 | I16: =I5*I11 -> 633.19519 | ... K16: =K5*K11 -> 930.79693
A17: Mid ADV tokenized mkt cap ($Bn) | B17: =B6*B12 -> 0 | C17: =C6*C12 -> 21 | D17: =D6*D12 -> 55.125 | E17: =E6*E12 -> 138.915 | F17: =F6*F12 -> 303.87656 | G17: =G6*G12 -> 510.51263 | H17: =H6*H12 -> 804.05738 | I17: =I6*I12 -> 1125.6803 | ... K17: =K6*K12 -> 1861.5939
A18: High ADV tokenized mkt cap ($Bn) | B18: =B7*B13 -> 0 | C18: =C7*C13 -> 0 | D18: =D7*D13 -> 49.6125 | E18: =E7*E13 -> 156.27938 | F18: =F7*F13 -> 328.18669 | G18: =G7*G13 -> 574.3267 | H18: =H7*H13 -> 1206.0861 | I18: =I7*I13 -> 1899.5856 | ... K18: =K7*K13 -> 3490.4885
A20: Total tokenized equity market cap ($Bn) | B20: =SUM(B16:B18) -> 3 | C20: =SUM(C16:C18) -> 36.75 | D20: =SUM(D16:D18) -> 154.35 | E20: =SUM(E16:E18) -> 416.745 | F20: =SUM(F16:F18) -> 850.85438 | G20: =SUM(G16:G18) -> 1429.4354 | H20: =SUM(H16:H18) -> 2492.5779 | I20: =SUM(I16:I18) -> 3658.4611 | ... K20: =SUM(K16:K18) -> 6282.8793
A21: Blended penetration (% of total mkt cap) | B21: =B20/B8 -> 5.1724138e-05 | C21: =C20/C8 -> 0.00060344828 | D21: =D20/D8 -> 0.0024137931 | E21: =E20/E8 -> 0.0062068966 | F21: =F20/F8 -> 0.012068966 | G21: =G20/G8 -> 0.019310345 | H21: =H20/H8 -> 0.032068966 | I21: =I20/I8 -> 0.044827586 | ... K21: =K20/K8 -> 0.069827586
A23: CONTRIBUTION BREAKDOWN
A24: Low ADV % of tokenized total | B24: =IF(B20=0,0,B16/B20) -> 1 | C24: =IF(C20=0,0,C16/C20) -> 0.42857143 | D24: =IF(D20=0,0,D16/D20) -> 0.32142857 | E24: =IF(E20=0,0,E16/E20) -> 0.29166667 | F24: =IF(F20=0,0,F16/F20) -> 0.25714286 | G24: =IF(G20=0,0,G16/G20) -> 0.24107143 | H24: =IF(H20=0,0,H16/H20) -> 0.19354839 | I24: =IF(I20=0,0,I16/I20) -> 0.17307692 | ... K24: =IF(K20=0,0,K16/K20) -> 0.14814815
A25: Mid ADV % of tokenized total | B25: =IF(B20=0,0,B17/B20) -> 0 | C25: =IF(C20=0,0,C17/C20) -> 0.57142857 | D25: =IF(D20=0,0,D17/D20) -> 0.35714286 | E25: =IF(E20=0,0,E17/E20) -> 0.33333333 | F25: =IF(F20=0,0,F17/F20) -> 0.35714286 | G25: =IF(G20=0,0,G17/G20) -> 0.35714286 | H25: =IF(H20=0,0,H17/H20) -> 0.32258065 | I25: =IF(I20=0,0,I17/I20) -> 0.30769231 | ... K25: =IF(K20=0,0,K17/K20) -> 0.2962963
A26: High ADV % of tokenized total | B26: =IF(B20=0,0,B18/B20) -> 0 | C26: =IF(C20=0,0,C18/C20) -> 0 | D26: =IF(D20=0,0,D18/D20) -> 0.32142857 | E26: =IF(E20=0,0,E18/E20) -> 0.375 | F26: =IF(F20=0,0,F18/F20) -> 0.38571429 | G26: =IF(G20=0,0,G18/G20) -> 0.40178571 | H26: =IF(H20=0,0,H18/H20) -> 0.48387097 | I26: =IF(I20=0,0,I18/I20) -> 0.51923077 | ... K26: =IF(K20=0,0,K18/K20) -> 0.55555556
A28: IMPLIED TOKENIZED ISSUERS (APPROX)
A29: Low ADV issuers tokenized | B29: =Assumptions!B12*Assumptions!B21 -> 2.4 | C29: =Assumptions!B12*Assumptions!B22 -> 12 | D29: =Assumptions!B12*Assumptions!B23 -> 36 | E29: =Assumptions!B12*Assumptions!B24 -> 84 | F29: =Assumptions!B12*Assumptions!B25 -> 144 | G29: =Assumptions!B12*Assumptions!B26 -> 216 | H29: =Assumptions!B12*Assumptions!B27 -> 288 | I29: =Assumptions!B12*Assumptions!B28 -> 360 | J29: =Assumptions!B12*Assumptions!B29 -> 432 | K29: =Assumptions!B12*Assumptions!B30 -> 480
A30: Mid ADV issuers tokenized | B30: =Assumptions!C12*Assumptions!C21 -> 0 | C30: =Assumptions!C12*Assumptions!C22 -> 3 | D30: =Assumptions!C12*Assumptions!C23 -> 7.5 | E30: =Assumptions!C12*Assumptions!C24 -> 18 | F30: =Assumptions!C12*Assumptions!C25 -> 37.5 | G30: =Assumptions!C12*Assumptions!C26 -> 60 | H30: =Assumptions!C12*Assumptions!C27 -> 90 | I30: =Assumptions!C12*Assumptions!C28 -> 120 | J30: =Assumptions!C12*Assumptions!C29 -> 150 | K30: =Assumptions!C12*Assumptions!C30 -> 180
A31: High ADV issuers tokenized | B31: =Assumptions!D12*Assumptions!D21 -> 0 | C31: =Assumptions!D12*Assumptions!D22 -> 0 | D31: =Assumptions!D12*Assumptions!D23 -> 0.5 | E31: =Assumptions!D12*Assumptions!D24 -> 1.5 | F31: =Assumptions!D12*Assumptions!D25 -> 3 | G31: =Assumptions!D12*Assumptions!D26 -> 5 | H31: =Assumptions!D12*Assumptions!D27 -> 10 | I31: =Assumptions!D12*Assumptions!D28 -> 15 | J31: =Assumptions!D12*Assumptions!D29 -> 20 | K31: =Assumptions!D12*Assumptions!D30 -> 25
A32: Total tokenized issuers | B32: =SUM(B29:B31) -> 2.4 | C32: =SUM(C29:C31) -> 15 | D32: =SUM(D29:D31) -> 44 | E32: =SUM(E29:E31) -> 103.5 | F32: =SUM(F29:F31) -> 184.5 | G32: =SUM(G29:G31) -> 281 | H32: =SUM(H29:H31) -> 388 | I32: =SUM(I29:I31) -> 495 | ... K32: =SUM(K29:K31) -> 685

Sheet Revenue Pools
A1: Tokenized US Equity Revenue Pool Analysis ($M)
A2: Annual revenue by segment, linked to base case tokenized market cap projection
B4: Assumption | C4: 2026 | D4: 2027 | E4: 2028 | F4: 2029 | G4: 2030 | H4: 2031 | I4: 2032 | J4: 2033 | K4: 2034 | L4: 2035 | M4: Source / Rationale
A5: INPUTS (FROM PROJECTION SHEET)
A6: Total tokenized equity mkt cap ($Bn) | C6: =Projection!B20 -> 3 | D6: =Projection!C20 -> 36.75 | E6: =Projection!D20 -> 154.35 | F6: =Projection!E20 -> 416.745 | G6: =Projection!F20 -> 850.85438 | H6: =Projection!G20 -> 1429.4354 | I6: =Projection!H20 -> 2492.5779 | J6: =Projection!I20 -> 3658.4611 | ... L6: =Projection!K20 -> 6282.8793
A7: Total tokenized equity mkt cap ($M) | C7: =C6*1000 -> 3000 | D7: =D6*1000 -> 36750 | E7: =E6*1000 -> 154350 | F7: =F6*1000 -> 416745 | G7: =G6*1000 -> 850854.38 | H7: =H6*1000 -> 1429435.4 | I7: =I6*1000 -> 2492577.9 | J7: =J6*1000 -> 3658461.1 | ... L7: =L6*1000 -> 6282879.3 | M7: Conversion for revenue calc
A9: 1. TRADING REVENUE
A10: Annual turnover velocity (x mkt cap) | C10: 0.8 | D10: 1 | E10: 1.2 | F10: 1.4 | G10: 1.6 | H10: 1.8 | I10: 2 | J10: 2.2 | K10: 2.4 | L10: 2.5 | M10: US equity avg ~2.5x; lower early (fewer market makers), ramping to mature
A11: Implied annual trading volume ($M) | C11: =C7*C10 -> 2400 | D11: =D7*D10 -> 36750 | E11: =E7*E10 -> 185220 | F11: =F7*F10 -> 583443 | G11: =G7*G10 -> 1361367 | H11: =H7*H10 -> 2572983.6 | I11: =I7*I10 -> 4985155.8 | J11: =J7*J10 -> 8048614.4 | ... L11: =L7*L10 -> 15707198
A12: Blended take rate (bps on volume) | C12: 8 | D12: 7 | E12: 6 | F12: 5.5 | G12: 5 | H12: 4.5 | I12: 4 | J12: 3.5 | K12: 3 | L12: 2.5 | M12: Includes exchange fees + maker/taker + spread capture; compresses with scale. Trad equity ~1-3bps exchange + 2-5bps spread
A13: Trading revenue ($M) | C13: =C11*C12/10000 -> 1.92 | D13: =D11*D12/10000 -> 25.725 | E13: =E11*E12/10000 -> 111.132 | F13: =F11*F12/10000 -> 320.89365 | G13: =G11*G12/10000 -> 680.6835 | H13: =H11*H12/10000 -> 1157.8426 | I13: =I11*I12/10000 -> 1994.0623 | J13: =J11*J12/10000 -> 2817.015 | ... L13: =L11*L12/10000 -> 3926.7995
A15: 2. MARGIN & SECURITIES LENDING REVENUE
A16: % of tokenized mkt cap available for lending | C16: 0.05 | D16: 0.08 | E16: 0.1 | F16: 0.12 | G16: 0.14 | H16: 0.15 | I16: 0.16 | J16: 0.17 | K16: 0.18 | L16: 0.2 | M16: Trad equities: ~15-20% of float in lending programs; lower early for tokenized due to custody maturity
A17: Lendable pool ($M) | C17: =C7*C16 -> 150 | D17: =D7*D16 -> 2940 | E17: =E7*E16 -> 15435 | F17: =F7*F16 -> 50009.4 | G17: =G7*G16 -> 119119.61 | H17: =H7*H16 -> 214415.3 | I17: =I7*I16 -> 398812.46 | J17: =J7*J16 -> 621938.39 | ... L17: =L7*L16 -> 1256575.9
A18: Utilization rate | C18: 0.15 | D18: 0.18 | E18: 0.22 | F18: 0.25 | G18: 0.28 | H18: 0.3 | I18: 0.32 | J18: 0.33 | K18: 0.34 | L18: 0.35 | M18: US sec lending utilization avg ~25-35%; on-chain collateral mobility could push higher over time
A19: On-loan balance ($M) | C19: =C17*C18 -> 22.5 | D19: =D17*D18 -> 529.2 | E19: =E17*E18 -> 3395.7 | F19: =F17*F18 -> 12502.35 | G19: =G17*G18 -> 33353.492 | H19: =H17*H18 -> 64324.591 | I19: =I17*I18 -> 127619.99 | J19: =J17*J18 -> 205239.67 | ... L19: =L17*L18 -> 439801.55
A20: Avg lending fee (bps, annualized) | C20: 50 | D20: 45 | E20: 40 | F20: 38 | G20: 35 | H20: 32 | I20: 30 | J20: 28 | K20: 26 | L20: 25 | M20: GC rate ~25-40bps; specials higher; blended avg ~30-50bps. Source: Markit Securities Finance, IHS
A21: Gross lending revenue ($M) | C21: =C19*C20/10000 -> 0.1125 | D21: =D19*D20/10000 -> 2.3814 | E21: =E19*E20/10000 -> 13.5828 | F21: =F19*F20/10000 -> 47.50893 | G21: =G19*G20/10000 -> 116.73722 | H21: =H19*H20/10000 -> 205.83869 | I21: =I19*I20/10000 -> 382.85996 | J21: =J19*J20/10000 -> 574.67107 | ... L21: =L19*L20/10000 -> 1099.5039
A22: Platform share of lending revenue (%) | C22: 0.35 | D22: 0.33 | E22: 0.3 | F22: 0.28 | G22: 0.27 | H22: 0.25 | I22: 0.24 | J22: 0.23 | K22: 0.22 | L22: 0.2 | M22: Agent lenders typically retain 20-35% of gross fee; higher early when fewer platforms compete
A23: Margin & sec lending revenue ($M) | C23: =C21*C22 -> 0.039375 | D23: =D21*D22 -> 0.785862 | E23: =E21*E22 -> 4.07484 | F23: =F21*F22 -> 13.3025 | G23: =G21*G22 -> 31.519049 | H23: =H21*H22 -> 51.459673 | I23: =I21*I22 -> 91.886391 | J23: =J21*J22 -> 132.17435 | ... L23: =L21*L22 -> 219.90077
A25: 3. PRIME BROKERAGE & CUSTODY REVENUE
A26: % of tokenized mkt cap under prime/custody | C26: 0.3 | D26: 0.35 | E26: 0.4 | F26: 0.45 | G26: 0.5 | H26: 0.55 | I26: 0.58 | J26: 0.6 | K26: 0.62 | L26: 0.65 | M26: Institutional AUM under prime ~60-70% for trad equities; lower early as institutional infra develops
A27: Assets under prime/custody ($M) | C27: =C7*C26 -> 900 | D27: =D7*D26 -> 12862.5 | E27: =E7*E26 -> 61740 | F27: =F7*F26 -> 187535.25 | G27: =G7*G26 -> 425427.19 | H27: =H7*H26 -> 786189.44 | I27: =I7*I26 -> 1445695.2 | J27: =J7*J26 -> 2195076.7 | ... L27: =L7*L26 -> 4083871.5
A28: Blended custody + prime fee (bps on AUC) | C28: 12 | D28: 11 | E28: 10 | F28: 9 | G28: 8 | H28: 7 | I28: 6.5 | J28: 6 | K28: 5.5 | L28: 5 | M28: Trad custody 1-5bps; digital asset custody premium 10-15bps early, compressing. COIN charges 10-50bps custody
A29: Prime brokerage & custody revenue ($M) | C29: =C27*C28/10000 -> 1.08 | D29: =D27*D28/10000 -> 14.14875 | E29: =E27*E28/10000 -> 61.74 | F29: =F27*F28/10000 -> 168.78172 | G29: =G27*G28/10000 -> 340.34175 | H29: =H27*H28/10000 -> 550.33261 | I29: =I27*I28/10000 -> 939.70187 | J29: =J27*J28/10000 -> 1317.046 | ... L29: =L27*L28/10000 -> 2041.9358
A31: 4. NEW ISSUANCE & TOKENIZATION FEES
A32: New issuers tokenizing per year | C32: =Projection!B32 -> 2.4 | D32: =Projection!C32-Projection!B32 -> 12.6 | E32: =Projection!D32-Projection!C32 -> 29 | F32: =Projection!E32-Projection!D32 -> 59.5 | G32: =Projection!F32-Projection!E32 -> 81 | H32: =Projection!G32-Projection!F32 -> 96.5 | I32: =Projection!H32-Projection!G32 -> 107 | J32: =Projection!I32-Projection!H32 -> 107 | K32: =Projection!J32-Projection!I32 -> 107 | L32: =Projection!K32-Projection!J32 -> 83 | M32: Incremental new tokenized issuers per year, from Projection sheet
A33: Avg issuance / tokenization fee per issuer ($K) | C33: 500 | D33: 450 | E33: 400 | F33: 375 | G33: 350 | H33: 325 | I33: 300 | J33: 275 | K33: 250 | L33: 225 | M33: Includes TA migration, smart contract deployment, legal/compliance. IPO fees 3-7% but tokenization is simpler; est $200-500K
A34: Issuance fee revenue ($M) | C34: =C32*C33/1000 -> 1.2 | D34: =D32*D33/1000 -> 5.67 | E34: =E32*E33/1000 -> 11.6 | F34: =F32*F33/1000 -> 22.3125 | G34: =G32*G33/1000 -> 28.35 | H34: =H32*H33/1000 -> 31.3625 | I34: =I32*I33/1000 -> 32.1 | J34: =J32*J33/1000 -> 29.425 | ... L34: =L32*L33/1000 -> 18.675
A35: Annual TA / record-keeping fee per issuer ($K) | C35: 150 | D35: 145 | E35: 140 | F35: 135 | G35: 130 | H35: 125 | I35: 120 | J35: 115 | K35: 110 | L35: 100 | M35: Trad TA fees ~$50-150K/yr per issuer; on-chain TA may command premium early. Source: Computershare/AST pricing
A36: Cumulative tokenized issuers | C36: =Projection!B32 -> 2.4 | D36: =Projection!C32 -> 15 | E36: =Projection!D32 -> 44 | F36: =Projection!E32 -> 103.5 | G36: =Projection!F32 -> 184.5 | H36: =Projection!G32 -> 281 | I36: =Projection!H32 -> 388 | J36: =Projection!I32 -> 495 | ... L36: =Projection!K32 -> 685
A37: Annual TA / record-keeping revenue ($M) | C37: =C36*C35/1000 -> 0.36 | D37: =D36*D35/1000 -> 2.175 | E37: =E36*E35/1000 -> 6.16 | F37: =F36*F35/1000 -> 13.9725 | G37: =G36*G35/1000 -> 23.985 | H37: =H36*H35/1000 -> 35.125 | I37: =I36*I35/1000 -> 46.56 | J37: =J36*J35/1000 -> 56.925 | ... L37: =L36*L35/1000 -> 68.5
A38: Total issuance + TA revenue ($M) | C38: =C34+C37 -> 1.56 | D38: =D34+D37 -> 7.845 | E38: =E34+E37 -> 17.76 | F38: =F34+F37 -> 36.285 | G38: =G34+G37 -> 52.335 | H38: =H34+H37 -> 66.4875 | I38: =I34+I37 -> 78.66 | J38: =J34+J37 -> 86.35 | ... L38: =L34+L37 -> 87.175
A40: 5. MARKET DATA & INDEX LICENSING
A41: Market data rev as % of trading rev | C41: 0.1 | D41: 0.12 | E41: 0.14 | F41: 0.15 | G41: 0.16 | H41: 0.17 | I41: 0.18 | J41: 0.19 | K41: 0.2 | L41: 0.2 | M41: NYSE/NASDAQ market data = ~15-25% of exchange rev; on-chain data inherently more transparent but feeds still monetizable
A42: Market data & index licensing revenue ($M) | C42: =C13*C41 -> 0.192 | D42: =D13*D41 -> 3.087 | E42: =E13*E41 -> 15.55848 | F42: =F13*F41 -> 48.134047 | G42: =G13*G41 -> 108.90936 | H42: =H13*H41 -> 196.83325 | I42: =I13*I41 -> 358.93122 | J42: =J13*J41 -> 535.23286 | ... L42: =L13*L41 -> 785.35991
A44: 6. SETTLEMENT & CLEARING FEES
A45: Number of trades (M, implied) | C45: =C11/C46 -> 0.48 | D45: =D11/D46 -> 4.59375 | E45: =E11/E46 -> 18.522 | F45: =F11/F46 -> 48.62025 | G45: =G11/G46 -> 90.7578 | H45: =H11/H46 -> 142.94354 | I45: =I11/I46 -> 226.59799 | J45: =J11/J46 -> 287.45051 | ... L45: =L11/L46 -> 373.98091
A46: Avg trade size ($) | C46: 5000 | D46: 8000 | E46: 10000 | F46: 12000 | G46: 15000 | H46: 18000 | I46: 22000 | J46: 28000 | K46: 35000 | L46: 42000 | M46: US equity avg ~$8-10K; tokenized skews smaller early (retail, fractional), grows with institutional adoption
A47: Settlement fee per trade ($) | C47: 0.1 | D47: 0.09 | E47: 0.08 | F47: 0.07 | G47: 0.06 | H47: 0.05 | I47: 0.05 | J47: 0.04 | K47: 0.04 | L47: 0.03 | M47: DTCC/NSCC equiv ~$0.01-0.05/trade; on-chain settlement costs gas + protocol fee; compresses with L2 scaling
A48: Settlement & clearing revenue ($M) | C48: =C45*C47 -> 0.048 | D48: =D45*D47 -> 0.4134375 | E48: =E45*E47 -> 1.48176 | F48: =F45*F47 -> 3.4034175 | G48: =G45*G47 -> 5.445468 | H48: =H45*H47 -> 7.1471768 | I48: =I45*I47 -> 11.3299 | J48: =J45*J47 -> 11.498021 | ... L48: =L45*L47 -> 11.219427
A50: TOTAL TOKENIZED EQUITY REVENUE POOL ($M)
A51: 1. Trading | C51: =C13 -> 1.92 | D51: =D13 -> 25.725 | E51: =E13 -> 111.132 | F51: =F13 -> 320.89365 | G51: =G13 -> 680.6835 | H51: =H13 -> 1157.8426 | I51: =I13 -> 1994.0623 | J51: =J13 -> 2817.015 | ... L51: =L13 -> 3926.7995
A52: 2. Margin & securities lending | C52: =C23 -> 0.039375 | D52: =D23 -> 0.785862 | E52: =E23 -> 4.07484 | F52: =F23 -> 13.3025 | G52: =G23 -> 31.519049 | H52: =H23 -> 51.459673 | I52: =I23 -> 91.886391 | J52: =J23 -> 132.17435 | ... L52: =L23 -> 219.90077
A53: 3. Prime brokerage & custody | C53: =C29 -> 1.08 | D53: =D29 -> 14.14875 | E53: =E29 -> 61.74 | F53: =F29 -> 168.78172 | G53: =G29 -> 340.34175 | H53: =H29 -> 550.33261 | I53: =I29 -> 939.70187 | J53: =J29 -> 1317.046 | ... L53: =L29 -> 2041.9358
A54: 4. Issuance + transfer agent fees | C54: =C38 -> 1.56 | D54: =D38 -> 7.845 | E54: =E38 -> 17.76 | F54: =F38 -> 36.285 | G54: =G38 -> 52.335 | H54: =H38 -> 66.4875 | I54: =I38 -> 78.66 | J54: =J38 -> 86.35 | ... L54: =L38 -> 87.175
A55: 5. Market data & index licensing | C55: =C42 -> 0.192 | D55: =D42 -> 3.087 | E55: =E42 -> 15.55848 | F55: =F42 -> 48.134047 | G55: =G42 -> 108.90936 | H55: =H42 -> 196.83325 | I55: =I42 -> 358.93122 | J55: =J42 -> 535.23286 | ... L55: =L42 -> 785.35991
A56: 6. Settlement & clearing | C56: =C48 -> 0.048 | D56: =D48 -> 0.4134375 | E56: =E48 -> 1.48176 | F56: =F48 -> 3.4034175 | G56: =G48 -> 5.445468 | H56: =H48 -> 7.1471768 | I56: =I48 -> 11.3299 | J56: =J48 -> 11.498021 | ... L56: =L48 -> 11.219427
A57: TOTAL REVENUE POOL ($M) | C57: =SUM(C51:C56) -> 4.839375 | D57: =SUM(D51:D56) -> 52.00505 | E57: =SUM(E51:E56) -> 211.74708 | F57: =SUM(F51:F56) -> 590.80034 | G57: =SUM(G51:G56) -> 1219.2341 | H57: =SUM(H51:H56) -> 2030.1028 | I57: =SUM(I51:I56) -> 3474.5717 | J57: =SUM(J51:J56) -> 4899.3163 | ... L57: =SUM(L51:L56) -> 7072.3904
A58: Total revenue pool ($Bn) | C58: =C57/1000 -> 0.004839375 | D58: =D57/1000 -> 0.05200505 | E58: =E57/1000 -> 0.21174708 | F58: =F57/1000 -> 0.59080034 | G58: =G57/1000 -> 1.2192341 | H58: =H57/1000 -> 2.0301028 | I58: =I57/1000 -> 3.4745717 | J58: =J57/1000 -> 4.8993163 | ... L58: =L57/1000 -> 7.0723904
A60: REVENUE MIX (% OF TOTAL)
A61: Trading | C61: =IF(C57=0,0,C51/C57) -> 0.39674545 | D61: =IF(D57=0,0,D51/D57) -> 0.4946635 | E61: =IF(E57=0,0,E51/E57) -> 0.52483368 | F61: =IF(F57=0,0,F51/F57) -> 0.54315075 | G61: =IF(G57=0,0,G51/G57) -> 0.55828777 | H61: =IF(H57=0,0,H51/H57) -> 0.57033694 | I61: =IF(I57=0,0,I51/I57) -> 0.57390162 | J61: =IF(J57=0,0,J51/J57) -> 0.57498126 | ... L61: =IF(L57=0,0,L51/L57) -> 0.55522946
A62: Margin & sec lending | C62: =IF(C57=0,0,C52/C57) -> 0.0081363812 | D62: =IF(D57=0,0,D52/D57) -> 0.015111263 | E62: =IF(E57=0,0,E52/E57) -> 0.019243902 | F62: =IF(F57=0,0,F52/F57) -> 0.022516068 | G62: =IF(G57=0,0,G52/G57) -> 0.025851515 | H62: =IF(H57=0,0,H52/H57) -> 0.025348308 | I62: =IF(I57=0,0,I52/I57) -> 0.026445387 | J62: =IF(J57=0,0,J52/J57) -> 0.026978121 | ... L62: =IF(L57=0,0,L52/L57) -> 0.03109285
A63: Prime & custody | C63: =IF(C57=0,0,C53/C57) -> 0.22316931 | D63: =IF(D57=0,0,D53/D57) -> 0.27206493 | E63: =IF(E57=0,0,E53/E57) -> 0.29157427 | F63: =IF(F57=0,0,F53/F57) -> 0.28568319 | G63: =IF(G57=0,0,G53/G57) -> 0.27914388 | H63: =IF(H57=0,0,H53/H57) -> 0.27108607 | I63: =IF(I57=0,0,I53/I57) -> 0.27045114 | J63: =IF(J57=0,0,J53/J57) -> 0.26882241 | ... L63: =IF(L57=0,0,L53/L57) -> 0.28871932
A64: Issuance + TA | C64: =IF(C57=0,0,C54/C57) -> 0.32235568 | D64: =IF(D57=0,0,D54/D57) -> 0.15085074 | E64: =IF(E57=0,0,E54/E57) -> 0.083873648 | F64: =IF(F57=0,0,F54/F57) -> 0.061416688 | G64: =IF(G57=0,0,G54/G57) -> 0.042924487 | H64: =IF(H57=0,0,H54/H57) -> 0.032750804 | I64: =IF(I57=0,0,I54/I57) -> 0.022638762 | J64: =IF(J57=0,0,J54/J57) -> 0.017624908 | ... L64: =IF(L57=0,0,L54/L57) -> 0.012326101
A65: Market data | C65: =IF(C57=0,0,C55/C57) -> 0.039674545 | D65: =IF(D57=0,0,D55/D57) -> 0.05935962 | E65: =IF(E57=0,0,E55/E57) -> 0.073476716 | F65: =IF(F57=0,0,F55/F57) -> 0.081472613 | G65: =IF(G57=0,0,G55/G57) -> 0.089326043 | H65: =IF(H57=0,0,H55/H57) -> 0.096957279 | I65: =IF(I57=0,0,I55/I57) -> 0.10330229 | J65: =IF(J57=0,0,J55/J57) -> 0.10924644 | ... L65: =IF(L57=0,0,L55/L57) -> 0.11104589
A66: Settlement & clearing | C66: =IF(C57=0,0,C56/C57) -> 0.0099186362 | D66: =IF(D57=0,0,D56/D57) -> 0.0079499492 | E66: =IF(E57=0,0,E56/E57) -> 0.0069977824 | F66: =IF(F57=0,0,F56/F57) -> 0.0057606898 | G66: =IF(G57=0,0,G56/G57) -> 0.0044663021 | H66: =IF(H57=0,0,H56/H57) -> 0.0035205984 | I66: =IF(I57=0,0,I56/I57) -> 0.0032608046 | J66: =IF(J57=0,0,J56/J57) -> 0.0023468623 | ... L66: =IF(L57=0,0,L56/L57) -> 0.0015863699
A67: Check (should = 100%) | C67: =SUM(C61:C66) -> 1 | D67: =SUM(D61:D66) -> 1 | E67: =SUM(E61:E66) -> 1 | F67: =SUM(F61:F66) -> 1 | G67: =SUM(G61:G66) -> 1 | H67: =SUM(H61:H66) -> 1 | I67: =SUM(I61:I66) -> 1 | J67: =SUM(J61:J66) -> 1 | ... L67: =SUM(L61:L66) -> 1
A69: REVENUE YIELD (BPS ON TOKENIZED MKT CAP)
A70: Trading | C70: =IF(C7=0,0,C51/C7*10000) -> 6.4 | D70: =IF(D7=0,0,D51/D7*10000) -> 7 | E70: =IF(E7=0,0,E51/E7*10000) -> 7.2 | F70: =IF(F7=0,0,F51/F7*10000) -> 7.7 | G70: =IF(G7=0,0,G51/G7*10000) -> 8 | H70: =IF(H7=0,0,H51/H7*10000) -> 8.1 | I70: =IF(I7=0,0,I51/I7*10000) -> 8 | J70: =IF(J7=0,0,J51/J7*10000) -> 7.7 | ... L70: =IF(L7=0,0,L51/L7*10000) -> 6.25
A71: Margin & sec lending | C71: =IF(C7=0,0,C52/C7*10000) -> 0.13125 | D71: =IF(D7=0,0,D52/D7*10000) -> 0.21384 | E71: =IF(E7=0,0,E52/E7*10000) -> 0.264 | F71: =IF(F7=0,0,F52/F7*10000) -> 0.3192 | G71: =IF(G7=0,0,G52/G7*10000) -> 0.37044 | H71: =IF(H7=0,0,H52/H7*10000) -> 0.36 | I71: =IF(I7=0,0,I52/I7*10000) -> 0.36864 | J71: =IF(J7=0,0,J52/J7*10000) -> 0.361284 | ... L71: =IF(L7=0,0,L52/L7*10000) -> 0.35
A72: Prime & custody | C72: =IF(C7=0,0,C53/C7*10000) -> 3.6 | D72: =IF(D7=0,0,D53/D7*10000) -> 3.85 | E72: =IF(E7=0,0,E53/E7*10000) -> 4 | F72: =IF(F7=0,0,F53/F7*10000) -> 4.05 | G72: =IF(G7=0,0,G53/G7*10000) -> 4 | H72: =IF(H7=0,0,H53/H7*10000) -> 3.85 | I72: =IF(I7=0,0,I53/I7*10000) -> 3.77 | J72: =IF(J7=0,0,J53/J7*10000) -> 3.6 | ... L72: =IF(L7=0,0,L53/L7*10000) -> 3.25
A73: Issuance + TA | C73: =IF(C7=0,0,C54/C7*10000) -> 5.2 | D73: =IF(D7=0,0,D54/D7*10000) -> 2.1346939 | E73: =IF(E7=0,0,E54/E7*10000) -> 1.1506317 | F73: =IF(F7=0,0,F54/F7*10000) -> 0.87067631 | G73: =IF(G7=0,0,G54/G7*10000) -> 0.61508763 | H73: =IF(H7=0,0,H54/H7*10000) -> 0.46513121 | I73: =IF(I7=0,0,I54/I7*10000) -> 0.3155769 | J73: =IF(J7=0,0,J54/J7*10000) -> 0.2360282 | ... L73: =IF(L7=0,0,L54/L7*10000) -> 0.13875008
A74: Market data | C74: =IF(C7=0,0,C55/C7*10000) -> 0.64 | D74: =IF(D7=0,0,D55/D7*10000) -> 0.84 | E74: =IF(E7=0,0,E55/E7*10000) -> 1.008 | F74: =IF(F7=0,0,F55/F7*10000) -> 1.155 | G74: =IF(G7=0,0,G55/G7*10000) -> 1.28 | H74: =IF(H7=0,0,H55/H7*10000) -> 1.377 | I74: =IF(I7=0,0,I55/I7*10000) -> 1.44 | J74: =IF(J7=0,0,J55/J7*10000) -> 1.463 | ... L74: =IF(L7=0,0,L55/L7*10000) -> 1.25
A75: Settlement & clearing | C75: =IF(C7=0,0,C56/C7*10000) -> 0.16 | D75: =IF(D7=0,0,D56/D7*10000) -> 0.1125 | E75: =IF(E7=0,0,E56/E7*10000) -> 0.096 | F75: =IF(F7=0,0,F56/F7*10000) -> 0.081666667 | G75: =IF(G7=0,0,G56/G7*10000) -> 0.064 | H75: =IF(H7=0,0,H56/H7*10000) -> 0.05 | I75: =IF(I7=0,0,I56/I7*10000) -> 0.045454545 | J75: =IF(J7=0,0,J56/J7*10000) -> 0.031428571 | ... L75: =IF(L7=0,0,L56/L7*10000) -> 0.017857143
A76: Total yield (bps) | C76: =SUM(C70:C75) -> 16.13125 | D76: =SUM(D70:D75) -> 14.151034 | E76: =SUM(E70:E75) -> 13.718632 | F76: =SUM(F70:F75) -> 14.176543 | G76: =SUM(G70:G75) -> 14.329528 | H76: =SUM(H70:H75) -> 14.202131 | I76: =SUM(I70:I75) -> 13.939671 | J76: =SUM(J70:J75) -> 13.391741 | ... L76: =SUM(L70:L75) -> 11.256607
A78: REVENUE POOL → COMPANY MAPPING
A79: Trading | C79: COIN, FIGR (OPEN network), Bullish, Robinhood (HOOD), NYSE/ICE, NASDAQ
A80: Margin & sec lending | C80: COIN Prime, FIGR, Galaxy Digital, Anchorage, Fireblocks
A81: Prime brokerage & custody | C81: COIN Custody, Anchorage, Fireblocks, BitGo, BNY Mellon, State Street
A82: Issuance + TA fees | C82: FIGR (Securitize on OPEN), Securitize, DTCC, Computershare, AST Financial
A83: Market data & index licensing | C83: CRCL (on-chain data layer), Kaiko, Pyth, Chainlink, ICE, NASDAQ
A84: Settlement & clearing | C84: CRCL (USDC settlement), FIGR (OPEN), DTCC, Paxos, Fireblocks
A86: KEY SOURCES
A87: Trading fee benchmarks | C87: SIFMA US Equity Market Structure | E87: https://www.sifma.org/resources/research/us-equity-markets-statistics/
A88: Securities lending data | C88: IHS Markit Securities Finance | E88: https://ihsmarkit.com/products/securities-finance.html
A89: Custody fee benchmarks | C89: Coinbase Institutional pricing | E89: https://www.coinbase.com/institutional
A90: Transfer agent market | C90: SEC TA registration data | E90: https://www.sec.gov/cgi-bin/browse-edgar?action=getcompany&type=TA&dateb=&owner=include&count=40&search_text=&action=getcompany
A91: Exchange market data revenue | C91: ICE/NYSE 10-K, NASDAQ 10-K | E91: https://www.sec.gov/cgi-bin/browse-edgar?company=intercontinental+exchange&CIK=&type=10-K&dateb=&owner=include&count=10&search_text=&action=getcompany
A92: DTCC clearing fees | C92: DTCC fee schedules | E92: https://www.dtcc.com/clearing-services/equities-clearing-services/fees
A93: On-chain settlement costs | C93: Ethereum/L2 gas trackers | E93: https://etherscan.io/gastracker

Sheet Scenarios
A1: Scenario Sensitivity: Terminal Year (2035) Tokenized Market Cap
A3: Terminal penetration rate assumptions
B4: Bear | C4: Base | D4: Bull
A5: Low ADV terminal penetration | B5: 0.08 | C5: 0.2 | D5: 0.35 | F5: Source: Bernstein scenario analysis
A6: Mid ADV terminal penetration | B6: 0.04 | C6: 0.12 | D6: 0.25
A7: High ADV terminal penetration | B7: 0.01 | C7: 0.05 | D7: 0.12
A9: Terminal year (2035) segment mkt cap ($Bn)
A10: Low ADV mkt cap ($Bn, 2035E) | B10: =Assumptions!B13*(1+Assumptions!B33)^9 -> 4653.9846
A11: Mid ADV mkt cap ($Bn, 2035E) | B11: =Assumptions!C13*(1+Assumptions!B33)^9 -> 15513.282
A12: High ADV mkt cap ($Bn, 2035E) | B12: =Assumptions!D13*(1+Assumptions!B33)^9 -> 69809.77
A14: Tokenized market cap by scenario ($Bn)
B15: Bear | C15: Base | D15: Bull
A16: Low ADV tokenized ($Bn) | B16: =$B$10*B5 -> 372.31877 | C16: =$B$10*C5 -> 930.79693 | D16: =$B$10*D5 -> 1628.8946
A17: Mid ADV tokenized ($Bn) | B17: =$B$11*B6 -> 620.53129 | C17: =$B$11*C6 -> 1861.5939 | D17: =$B$11*D6 -> 3878.3205
A18: High ADV tokenized ($Bn) | B18: =$B$12*B7 -> 698.0977 | C18: =$B$12*C7 -> 3490.4885 | D18: =$B$12*D7 -> 8377.1724
A20: Total tokenized equity mkt cap ($Bn) | B20: =SUM(B16:B18) -> 1690.9478 | C20: =SUM(C16:C18) -> 6282.8793 | D20: =SUM(D16:D18) -> 13884.388
A21: Blended penetration | B21: =B20/($B$10+$B$11+$B$12) -> 0.018793103 | C21: =C20/($B$10+$B$11+$B$12) -> 0.069827586 | D21: =D20/($B$10+$B$11+$B$12) -> 0.15431034

Sheet Historical Analogues
A1: Historical Analogues: ETF & ADR Annual Growth Data
A2: Annual data series for benchmarking tokenized equity penetration assumptions
A4: US ETF MARKET — ANNUAL DATA (1993–2025) | G4: US ADR MARKET — ANNUAL DATA (1990–2025)
A5: Year | B5: ETF AUM ($Bn) | C5: US Eq Mkt Cap ($Bn) | D5: ETF Penetration (%) | E5: # of ETFs | G5: Year | H5: ADR Trading Val ($Bn/yr) | I5: US Eq Trading Val ($Bn/yr) | J5: ADR % of Trading | K5: ADR Mkt Cap ($Bn) | L5: US Eq Mkt Cap ($Bn) | M5: ADR % of Mkt Cap
A6: 1993 | B6: 0.5 | C6: 5137 | D6: =B6/C6 -> 9.7333074e-05 | E6: 1 | G6: 1990 | H6: 75 | I6: 1325 | J6: =H6/I6 -> 0.056603774 | K6: 120 | L6: 3060 | M6: =K6/L6 -> 0.039215686
A7: 1994 | B7: 0.4 | C7: 5068 | D7: =B7/C7 -> 7.8926598e-05 | E7: 1 | G7: 1991 | H7: 100 | I7: 1520 | J7: =H7/I7 -> 0.065789474 | K7: 165 | L7: 4090 | M7: =K7/L7 -> 0.040342298
A8: 1995 | B8: 1.1 | C8: 6858 | D8: =B8/C8 -> 0.00016039662 | E8: 2 | G8: 1992 | H8: 110 | I8: 1745 | J8: =H8/I8 -> 0.063037249 | K8: 170 | L8: 4485 | M8: =K8/L8 -> 0.037904125
A9: 1996 | B9: 2.4 | C9: 8484 | D9: =B9/C9 -> 0.00028288543 | E9: 19 | G9: 1993 | H9: 135 | I9: 2081 | J9: =H9/I9 -> 0.064872657 | K9: 210 | L9: 5137 | M9: =K9/L9 -> 0.040879891
A10: 1997 | B10: 6.7 | C10: 10880 | D10: =B10/C10 -> 0.00061580882 | E10: 19 | G10: 1994 | H10: 140 | I10: 2454 | J10: =H10/I10 -> 0.057049715 | K10: 200 | L10: 5068 | M10: =K10/L10 -> 0.039463299
A11: 1998 | B11: 16 | C11: 13451 | D11: =B11/C11 -> 0.0011895026 | E11: 29 | G11: 1995 | H11: 152 | I11: 3083 | J11: =H11/I11 -> 0.049302627 | K11: 310 | L11: 6858 | M11: =K11/L11 -> 0.045202683
A12: 1999 | B12: 34 | C12: 16635 | D12: =B12/C12 -> 0.0020438834 | E12: 30 | G12: 1996 | H12: 195 | I12: 4064 | J12: =H12/I12 -> 0.047982283 | K12: 405 | L12: 8484 | M12: =K12/L12 -> 0.047736917
A13: 2000 | B13: 66 | C13: 15104 | D13: =B13/C13 -> 0.0043697034 | E13: 80 | G13: 1997 | H13: 275 | I13: 5778 | J13: =H13/I13 -> 0.047594323 | K13: 520 | L13: 10880 | M13: =K13/L13 -> 0.047794118
A14: 2001 | B14: 84 | C14: 13855 | D14: =B14/C14 -> 0.0060627932 | E14: 102 | G14: 1998 | H14: 340 | I14: 7318 | J14: =H14/I14 -> 0.046460782 | K14: 580 | L14: 13451 | M14: =K14/L14 -> 0.043119471
A15: 2002 | B15: 102 | C15: 10049 | D15: =B15/C15 -> 0.010150264 | E15: 113 | G15: 1999 | H15: 597 | I15: 14223 | J15: =H15/I15 -> 0.041974267 | K15: 980 | L15: 16635 | M15: =K15/L15 -> 0.058911933
A16: 2003 | B16: 151 | C16: 14266 | D16: =B16/C16 -> 0.010584607 | E16: 119 | G16: 2000 | H16: 560 | I16: 14954 | J16: =H16/I16 -> 0.037448174 | K16: 850 | L16: 15104 | M16: =K16/L16 -> 0.056276483
A17: 2004 | B17: 228 | C17: 16324 | D17: =B17/C17 -> 0.013967165 | E17: 152 | G17: 2001 | H17: 382 | I17: 10311 | J17: =H17/I17 -> 0.037047813 | K17: 550 | L17: 13855 | M17: =K17/L17 -> 0.03969686
... A38: 2025 | B38: 10500 | C38: 58000 | D38: =B38/C38 -> 0.18103448 | E38: 3800 | G38: 2022 | H38: 1180 | I38: 53200 | J38: =H38/I38 -> 0.022180451 | K38: 3500 | L38: 40360 | M38: =K38/L38 -> 0.086719524
G39: 2023 | H39: 1250 | I39: 56500 | J39: =H39/I39 -> 0.022123894 | K39: 3900 | L39: 50788 | M39: =K39/L39 -> 0.076789793
A40: Summary | G40: 2024 | H40: 1350 | I40: 59400 | J40: =H40/I40 -> 0.022727273 | K40: 3950 | L40: 55200 | M40: =K40/L40 -> 0.071557971
A41: Yr 5 | B41: =B10 -> 6.7 | D41: =D10 -> 0.00061580882 | G41: 2025 | H41: 1400 | I41: 62000 | J41: =H41/I41 -> 0.022580645 | K41: 4000 | L41: 58000 | M41: =K41/L41 -> 0.068965517
A42: Yr 10 | B42: =B15 -> 102 | D42: =D15 -> 0.010150264
A43: Yr 15 | B43: =B20 -> 608 | D43: =D20 -> 0.030479246 | G43: Summary
A44: Yr 20 | B44: =B25 -> 1337 | D44: =D25 -> 0.071619884 | G44: Avg ADR % trading (all years) | J44: =AVERAGE(J6:J41) -> 0.041650407
A45: Yr 30 | B45: =B35 -> 6447 | D45: =D35 -> 0.15973736 | G45: Avg ADR % mkt cap (all years) | M45: =AVERAGE(M6:M41) -> 0.071285589
A46: Yr 32 | B46: =B38 -> 10500 | D46: =D38 -> 0.18103448 | G46: Peak ADR % trading | J46: =MAX(J6:J41) -> 0.065789474
G47: Peak ADR % mkt cap | M47: =MAX(M6:M41) -> 0.10527371
A48: Takeaway | B48: ETFs: <1% penetration through year 10; inflection around year 12-14 (~2-3%); crossed 5% at ~year 17; now ~18% at year 32. First decade = infrastructure + regulatory build; second decade = exponential adoption. | G48: Min ADR % trading | J48: =MIN(J6:J41) -> 0.022123894
G50: Takeaway | H50: ADRs: trading share ranged 2-6% over 35 years — remarkably stable niche, never achieved mass penetration. Mkt cap share higher at 4-11%, reflecting larger-cap bias in ADR listings. ADRs are a 'new wrapper for cross-border access' analogue — tokenization of US equities for global investors mirrors this pattern. But tokenization also offers settlement/collateral benefits that ADRs don't, suggesting higher terminal penetration.
A51: Sources | B51: ICI Fact Book
B52: ETF.com
B53: SIFMA Capital Markets Fact Book | G53: Sources | H53: BNY Mellon DR Directory
B54: S&P Global Market Intelligence | H54: BNY Mellon DR Market Review (annual)
B55: 2024-2025E: Bernstein estimates | H55: SIFMA US Equity Market Statistics
H56: World Federation of Exchanges
H57: 2024-2025E: Bernstein estimates
A59: ANALOGUE COMPARISON: PENETRATION MILESTONES
B60: Launch | C60: Yr 5 Pen. | D60: Yr 10 Pen. | E60: Yr 15 Pen. | F60: Yr 20 Pen. | G60: Current Pen. | H60: Terminal View | I60: Primary Driver
A61: US ETFs | B61: 1993 | C61: =D10 -> 0.00061580882 | D61: =D15 -> 0.010150264 | E61: =D20 -> 0.030479246 | F61: =D25 -> 0.071619884 | G61: =D38 -> 0.18103448 | H61: 20-25% | I61: New product wrapper; tax efficiency
A62: US ADRs | B62: 1990 | C62: =J10 -> 0.057049715 | D62: =J15 -> 0.041974267 | E62: =J20 -> 0.044758134 | F62: =J25 -> 0.038594755 | G62: =J41 -> 0.022580645 | H62: 2-5% | I62: Cross-border access wrapper; stable niche
A63: Tokenized US equities | B63: 2026 | C63: =Projection!F21 -> 0.012068966 | D63: =Projection!K21 -> 0.069827586 | E63: N/A | F63: N/A | G63: N/A | H63: 5-12% | I63: New rail; 24/7 settlement, global access, collateral
A65: Implication | B65: Base case ~7% penetration at year 10 is aggressive vs. ETF precedent (1.1% at year 10) but conservative vs. the argument that tokenization is infrastructure migration, not a new product. ADR analogue suggests cross-border access alone could sustain 5-7%. Settlement and collateral benefits are additive. Bear case floors at ADR-like 2-5%; bull case could approach ETF-like trajectory with 10-15 year lag compression.
A68: Data notes | B68: ETF AUM: ICI Fact Book is canonical source; pre-2000 data from ETF.com archives. ADR data: BNY Mellon annual DR Market Reviews are primary source; trading values before 2000 are estimated from WFE/SIFMA aggregates. US equity mkt cap: S&P Global / Wilshire 5000 total market index. 2024-2025E figures are Bernstein estimates. Cross-verify ADR trading values against BNY Mellon's published annual reviews on your terminal.
