Workbook

Sheet Read Me
A1: US Tokenized Equity TAM Model | v7.0
A2: Rebuilt 27-Aug-2026. Every hard input carries a source ID and a clickable link. Forecast inputs are flagged and listed on the Audit tab.
A4: WHAT THIS MODEL DOES
A5: Question | B5: How large is the addressable market for tokenized US listed equities, and what annual revenue pool does it support, 2026-2035?
A6: Method | B6: Segment the US listed market on the Russell index boundary, project penetration with a logistic adoption curve anchored to the observed on-chain base, then apply revenue rates computed from disclosed company and industry figures.
A7: Unit convention | B7: $Bn for market cap and volume. $M for revenue. bps for take rates. Years are calendar.
A9: CELL COLOUR CONVENTION
A10: Blue text | B10: Hard input. This is the only kind of cell you should type into.
A11: Black text | B11: Formula. Do not overwrite.
A12: Blue underlined | B12: Clickable source link.
A14: INPUT STATUS FLAGS
A15: VERIFIED | B15: The figure appears verbatim in the linked primary document. Nothing has been adjusted.
A16: DERIVED | B16: Arithmetic on VERIFIED figures only (e.g. a fee rate computed as disclosed revenue divided by disclosed balance). No judgement applied.
A17: FORECAST | B17: A forward-looking judgement. Cannot be sourced because the event has not happened. Every one is listed on the Audit tab with its rationale and the sourced reference points that bracket it.
A19: WHAT CHANGED FROM v6.1 - CORRECTIONS
A20: # | B20: Correction | C20: Status
A21: 1 | B21: Settlement fee was wrong by ~20-45x. v6.1 modelled $0.10 per trade and cited the NSCC fee filing as support. The filing sets $0.44 per MILLION DOLLARS of value into net, i.e. ~$0.004 on a $10,000 trade. Rebuilt on a value basis at the actual published rate. | C21: Fixed
A22: 2 | B22: Turnover assumption contradicted the model's own inputs. v6.1 asserted US equity turnover of ~2.5x market cap while separately carrying $1.1T ADV, which implies ~4.0x. Turnover is now a formula from ADV, trading days and market cap. | C22: Fixed
A23: 3 | B23: ETF analogue used the wrong numerator. v6.1 divided TOTAL ETF net assets (which include bond, commodity and international ETFs) by US equity market cap. Now uses ICI's domestic equity ETF line: 13.2% of US market cap, not the 20.9% the old basis produced. | C23: Fixed
A24: 4 | B24: Adoption sequencing was backwards. v6.1 assumed low-ADV small caps tokenize first. The SEC's no-action letter scopes DTCC's service to the Russell 1000, and every one of the ten largest tokenized stocks is a mega cap or index ETF. Segments re-ordered: large caps lead. | C24: Fixed
A25: 5 | B25: Segmentation had no public source. v6.1 split the market into ADV buckets described as a Bernstein estimate off a Bloomberg screen. Replaced with the Russell 1000 / 2000 / non-index boundary, which is published, reconstituted annually, and is the actual regulatory perimeter. | C25: Fixed
A26: 6 | B26: Two different US market cap figures coexisted. v6.1 carried $66.0T on Assumptions and $64.5T and $58.0T on the analogues tab for overlapping periods. Single sourced figure now used throughout. | C26: Fixed
A27: 7 | B27: Stale market data. v6.1 used SIFMA 1Q26 ($66.0T, 5,492 companies). Updated to 2Q26 ($76.9T, 5,532 companies). | C27: Updated
A28: 8 | B28: Narrative contradicted the arithmetic. v6.1 stated ETFs were at ~18% penetration in year 32; its own cells computed 20.9%. All narrative figures now read from cells. | C28: Fixed
A29: 9 | B29: One SEC URL was cited for two different documents. The same PDF was footnoted as both the DTCC no-action letter and NSCC rule filing SR-NSCC-2025-017. Separated and each replaced with its own primary link. | C29: Fixed
A30: 10 | B30: Broken and generic links. The CLARITY Act link had no bill number; NYSE, Figure, Robinhood and S&P Global were cited by homepage. All links now resolve to the specific document supporting the specific figure. | C30: Fixed
A31: 11 | B31: A Wikipedia page was cited as the authority for DTCC's tokenization mandate. Replaced with DTCC's own release and the SEC no-action letter coverage. | C31: Fixed
A32: 12 | B32: Take rates had no anchor. The 8bps starting rate was unsourced. Now interpolated between two disclosed rates: Robinhood's retail equity capture (1.3bps) and Coinbase's institutional spot capture (8.6bps). | C32: Fixed
... A38: 18 | B38: Scenarios stopped at market cap, and varied only the ceiling. Bear/base/bull now vary ceiling and curve steepness together and flow all the way through to the revenue pool. | C38: Added
A40: HOW TO DRIVE IT
B41: - Change the terminal penetration ceilings and the curve steepness on Inputs rows 34-39. Everything downstream reflows.
B42: - To impose your own year-by-year penetration path, type it into the override rows on the Penetration tab. Any cell you fill overrides the curve; any cell you leave blank keeps it.
B43: - Scenario ceilings sit on the Scenarios tab and are deliberately set to the sourced analogues: the bear case is the ADR outcome, the bull case is the domestic equity ETF outcome.
B44: - The Audit tab lists every forecast cell and every internal consistency check. Read it before circulating.

Sheet Sources
A1: Source Register
A2: Every hard input in this workbook points at one of these IDs. Links go to the exact document supporting the exact figure.
A4: ID | B4: Publisher | C4: Document and the exact figure it supports | D4: As of | E4: Link
A5: S01 | B5: SIFMA | C5: Research Quarterly: Equity & Related, 2Q26 - "Market cap of all US listed companies totaled $76.9T in 2Q26"; "number of listed companies stood at 5,532" | D5: 30-Jun-2026 | E5: =HYPERLINK("https://www.sifma.org/wp-content/uploads/2026/04/SIFMA-Research-Quarterly-Equity-and-Related-2Q26.pdf","open")
A6: S02 | B6: SIFMA | C6: Research Quarterly: Equity & Related (landing page, all quarters incl. 1Q26 $66.0T, -4.3% Q/Q) | D6: 2026 | E6: =HYPERLINK("https://www.sifma.org/research/statistics/research-quarterly-equity-and-related","open")
A7: S03 | B7: Cboe Global Markets | C7: 2025 US Equities Year in Review - "average daily notional value (ADNV) increasing 43.3% year-over-year to $1.1 trillion"; ADV 17.6bn shares | D7: FY2025 | E7: =HYPERLINK("https://www.cboe.com/insights/posts/2025-u-s-equities-year-in-review","open")
A8: S04 | B8: LSEG / FTSE Russell | C8: Russell Reconstitution June 2026 - Russell 3000 total mkt cap $75.6T (rank day 30-Apr-26); Russell 2000 $3.5T; R1000/R2000 breakpoint $5.7bn | D8: 30-Apr-2026 | E8: =HYPERLINK("https://www.lseg.com/en/insights/ftse-russell/russell-reconstitution-june-2026-larger-leaders-stronger-small-caps","open")
A9: S05 | B9: DTCC | C9: "Paving the Way to Tokenized DTC-Custodied Assets" - SEC no-action letter dated 11-Dec-2025 covering the Russell 1000, index ETFs and US Treasuries; rollout 2H26; 3-year term | D9: 11-Dec-2025 | E9: =HYPERLINK("https://www.dtcc.com/news/2025/december/11/paving-the-way-to-tokenized-dtc-custodied-assets","open")
A10: S06 | B10: DTCC | C10: "DTCC Turns Tokenization into Reality" - live production trades processed 15-Jul-2026 with over 30 firms; the Industry Working Group "has grown in recent months to more than 100 members and partners"; "sets the stage for the DTCC Tokenization Service to launch in October 2026" | D10: 15-Jul-2026 | E10: =HYPERLINK("https://www.dtcc.com/press-releases/2026/dtcc-turns-tokenization-into-reality","open")
A11: S07 | B11: Crypto Times (data: Token Terminal) | C11: Tokenized RWA market $44.7bn; tokenized stocks $2.8bn (6.3% of RWA) | D11: 26-Aug-2026 | E11: =HYPERLINK("https://www.cryptotimes.io/2026/08/27/tokenized-rwa-market-hits-44-7b-as-funds-hold-76-4-share/","open")
A12: S08 | B12: Crypto Briefing (data: rwa.xyz) | C12: Tokenized stocks ~$2.5bn distributed value; total RWA $38.29bn; ~1.18m token holders | D12: 13-Aug-2026 | E12: =HYPERLINK("https://cryptobriefing.com/tokenized-stocks-rwa-market-cap-share/","open")
A13: S09 | B13: Webopedia | C13: Largest tokenized stocks by market cap - TSLAx, GOOGLx, NVDAx, CRCLx, QQQx, SPYx, MSTRx, AAPLx, COINx, GLDx (all Russell 1000 constituents or index ETFs) | D13: Jan-2026 | E13: =HYPERLINK("https://www.webopedia.com/crypto/learn/biggest-tokenized-stocks/","open")
A14: S10 | B14: ICI | C14: Exchange-Traded Fund Data, July 2026 - "The combined assets of the nation's exchange-traded funds (ETFs) were $15.67 trillion in July"; Total Domestic Equity $10,090.4bn; 5,182 ETFs | D14: 31-Jul-2026 | E14: =HYPERLINK("https://www.ici.org/research/stats/etf/etfs_04_26","open")
A15: S11 | B15: ICI | C15: 2026 Investment Company Fact Book, Ch.2 Fig 2.1 - ETF total net assets $13,373bn and 4,813 ETFs at YE2025; Fig 2.6 index domestic equity funds+ETFs = 19% of US stock market cap | D15: 31-Dec-2025 | E15: =HYPERLINK("https://icifactbook.org/pdf/2026-factbook-ch2.pdf","open")
A16: S12 | B16: ICI | C16: 2024 Investment Company Fact Book, Ch.4 Fig 4.1 - historical ETF total net assets (2000 $66bn, 2005 $301bn, 2010 $992bn) | D16: YE2023 | E16: =HYPERLINK("https://icifactbook.org/pdf/2024-factbook-ch4.pdf","open")
A17: S13 | B17: BNY | C17: Depositary Receipts Market Review 2025 - "$6.6T in DR value traded"; global DR investment $1.2T at YE25; 2,885 DR programs | D17: FY2025 | E17: =HYPERLINK("https://www.bny.com/assets/corporate/documents/pdf/year-In-review-v8.pdf","open")
A18: S14 | B18: S&P Global Market Intelligence (via Securities Finance Times) | C18: FY2025 securities lending - revenue $14.9bn (equities $11.5bn); average lendable $46.7T; average on-loan $3.25T | D18: FY2025 | E18: =HYPERLINK("https://www.securitiesfinancetimes.com/securitieslendingnews/industryarticle.php?article_id=228388","open")
A19: S15 | B19: EquiLend (via Hedgeweek) | C19: FY2025 global securities lending revenue $15.3bn, +26% Y/Y; loan balances topped $4T | D19: FY2025 | E19: =HYPERLINK("https://www.hedgeweek.com/global-securities-lending-revenue-hits-record-15-3bn-in-2025/","open")
A20: S16 | B20: Coinbase (SEC 8-K exhibit) | C20: Q4'25 Shareholder Letter - FY25 transaction revenue $4,055.4m on $5.2T total trading volume; Q4'25 consumer spot volume $56bn / revenue $734m; institutional spot $215bn / revenue $185m | D20: 31-Dec-2025 | E20: =HYPERLINK("https://www.sec.gov/Archives/edgar/data/1679788/000167978826000011/q425shareholderletter.htm","open")
A21: S17 | B21: Robinhood Markets | C21: Q4 and FY2025 Results - Q4'25 equities transaction revenue $94m on equity notional trading volume $710bn | D21: 31-Dec-2025 | E21: =HYPERLINK("https://investors.robinhood.com/node/15161/pdf","open")
A22: S18 | B22: Cboe Global Markets | C22: Q4 and FY2025 Results - US equities net capture $0.018 per 100 touched shares (on-exchange); $0.064 (off-exchange) | D22: 31-Dec-2025 | E22: =HYPERLINK("https://ir.cboe.com/news/news-details/2026/Cboe-Global-Markets-Reports-Results-for-Fourth-Quarter-2025-and-Full-Year/default.aspx","open")
A23: S19 | B23: BNY | C23: Q4 2025 Earnings Release - AUC/A $59.3T at 31-Dec-25; FY25 investment services fees $10,211m | D23: 31-Dec-2025 | E23: =HYPERLINK("https://www.bny.com/assets/corporate/documents/pdf/investor-relations/earnings/earnings-press-release-4q-2025.pdf","open")
A24: S20 | B24: Intercontinental Exchange | C24: FY2025 Results - Exchanges segment: transaction revenue net $3,885m; data and connectivity services $1,031m | D24: FY2025 | E24: =HYPERLINK("https://ir.theice.com/press/news-details/2026/Intercontinental-Exchange-Reports-Strong-Full-Year-2025-Results/default.aspx","open")
A25: S21 | B25: Nasdaq | C25: Q4 and FY2025 Results - Market Services net revenue $1,201m; Data and Listing Services $804m; Index $827m | D25: FY2025 | E25: =HYPERLINK("https://ir.nasdaq.com/node/109901/pdf","open")
A26: S22 | B26: DTCC | C26: Guide to the NSCC Fee Schedule - Clearance Activity, Value Into Net, Fee ID 2482. NOTE: the copy retrieved 10-Sep-2026 still displays 0.46; S23 is the authority for the 0.44 rate effective 01-Jan-2026 | D26: Jan-2026 | E26: =HYPERLINK("https://www.dtcc.com/-/media/Files/Downloads/legal/fee-guides/nsccfeeguide.pdf","open")
A27: S23 | B27: SEC | C27: SR-NSCC-2025-017 - "decrease its 'value into the net' fee from $0.46 to $0.44 per million of processed value"; "The proposed changes ... would be implemented on January 1, 2026" | D27: 17-Dec-2025 | E27: =HYPERLINK("https://www.federalregister.gov/documents/2025/12/17/2025-23068/self-regulatory-organizations-national-securities-clearing-corporation-notice-of-filing-and","open")
A28: S24 | B28: Securitize Corp (PR Newswire) | C28: Q2 2026 Results - revenue $14.4m (tokenization $7.8m, asset servicing $6.6m); average tokenized AUM $4.3bn; 663 funds serviced | D28: 30-Jun-2026 | E28: =HYPERLINK("https://www.prnewswire.com/news-releases/securitize-reports-second-quarter-2026-results-302850119.html","open")
A29: S25 | B29: Securitize Corp (PR Newswire) | C29: Q1 2026 Results - revenue $19.5m (tokenization $11.1m, asset servicing $8.3m); average tokenized AUM $3.2bn | D29: 31-Mar-2026 | E29: =HYPERLINK("https://www.prnewswire.com/news-releases/securitize-reports-first-quarter-2026-results-302777848.html","open")
A30: S26 | B30: Congress.gov | C30: H.R.3633 Digital Asset Market Clarity Act, 119th Congress - bill text and status | D30: 2026 | E30: =HYPERLINK("https://www.congress.gov/bill/119th-congress/house-bill/3633","open")
A31: S27 | B31: Disruption Banking | C31: CLARITY Act status - House passed 294-134 on 17-Jul-2025; Senate Banking advanced 15-9 on 14-May-2026; Senate Legislative Calendar No. 423 from 01-Jun-2026; not enacted | D31: 31-Jul-2026 | E31: =HYPERLINK("https://www.disruptionbanking.com/2026/07/31/clarity-act-update-where-the-crypto-market-structure-bill-stands-right-now/","open")
A32: S28 | B32: NYSE | C32: Holidays and Trading Hours - 2026 calendar. 365 days less 104 weekend days less 10 full-day closures = 251 trading days (independently cross-checked) | D32: 2026 | E32: =HYPERLINK("https://www.nyse.com/markets/hours-calendars","open")
A33: S29 | B33: Cadwalader | C33: SEC Staff Issues No-Action Relief for DTC Tokenization Pilot - legal analysis of the 11-Dec-2025 letter | D33: 18-Dec-2025 | E33: =HYPERLINK("https://www.cadwalader.com/fin-news/index.php?eid=1003&nid=142","open")
A34: S30 | B34: SIFMA | C34: Capital Markets Fact Book (annual reference for US equity market aggregates) | D34: 2025 | E34: =HYPERLINK("https://www.sifma.org/research/statistics/fact-book","open")
A35: S31 | B35: DTCC | C35: Annual Financial Statements 2025 - total revenues $2,895.8m, of which settlement and asset services $664.6m and clearing services $1,336.2m | D35: FY2025 | E35: =HYPERLINK("https://www.dtcc.com/-/media/Files/Downloads/legal/financials/2025/DTCC-Annual-Financial-Statement-2025.pdf","open")
A36: S32 | B36: DTCC | C36: "DTC assets under custody increased to $100.3 Trillion (2025) from $73.5 Trillion (2020)" - the denominator for DTCC's servicing yield | D36: 18-Jun-2025 | E36: =HYPERLINK("https://www.dtcc.com/news/2025/june/18/dtcc-central-securities-depository-subsidiary-surpasses-100-trillion-in-assets-under-custody","open")
A37: S33 | B37: Ondo Finance | C37: Ondo Stocks - more than $1bn TVL across 440+ tokenized stocks and ETFs; no explicit servicing or management fee is published, and ~2bps price impact on a $200k tokenized SPY trade is quoted | D37: Jul-2026 | E37: =HYPERLINK("https://ondo.finance/ondo-stocks","open")
A38: S34 | B38: DTCC | C38: Tokenization live production trades page - "about 40 firms participating", event dated 8 September, ahead of the October 2026 launch | D38: 08-Sep-2026 | E38: =HYPERLINK("https://www.dtcc.com/digital-assets/tokenization/live-production-trades","open")
A39: S35 | B39: SEC Division of Corporation Finance | C39: Statement on Tokenized Securities - stock remains an equity security regardless of format; issuer-sponsored, third-party custodial and third-party synthetic models | D39: 28-Jan-2026 | E39: =HYPERLINK("https://www.sec.gov/newsroom/speeches-statements/corp-fin-statement-tokenized-securities-012826-statement-tokenized-securities","open")
A40: S36 | B40: SEC | C40: Release No. 34-105047 - order approving Nasdaq rules for trading securities in tokenized form; fungible, same CUSIP and symbol, T+1 through DTC; Russell 1000 and major index ETFs | D40: 18-Mar-2026 | E40: =HYPERLINK("https://www.federalregister.gov/documents/2026/03/23/2026-05563/self-regulatory-organizations-the-nasdaq-stock-market-llc-order-approving-a-proposed-rule-change-as","open")

Sheet Inputs
A1: Inputs
A2: Blue cells are the only hard-coded numbers in the model. Status: VERIFIED = in the linked document. DERIVED = arithmetic on verified figures. FORECAST = judgement, listed on Audit.
A4: 1. US EQUITY MARKET - OBSERVED
A5: Input | B5: Value | C5: Unit | D5: Status | E5: Src | F5: Link | G5: Basis / derivation
A6: Total US equity market capitalisation | B6: 76900 | C6: $Bn | D6: VERIFIED | E6: S01 | F6: =HYPERLINK("https://www.sifma.org/wp-content/uploads/2026/04/SIFMA-Research-Quarterly-Equity-and-Related-2Q26.pdf","open") | G6: SIFMA 2Q26: "Market cap of all US listed companies totaled $76.9T in 2Q26"
A7: Total US listed companies | B7: 5532 | C7: count | D7: VERIFIED | E7: S01 | F7: =HYPERLINK("https://www.sifma.org/wp-content/uploads/2026/04/SIFMA-Research-Quarterly-Equity-and-Related-2Q26.pdf","open") | G7: SIFMA 2Q26: "the number of listed companies stood at 5,532"
A8: US equity average daily notional value | B8: 1100 | C8: $Bn/day | D8: VERIFIED | E8: S03 | F8: =HYPERLINK("https://www.cboe.com/insights/posts/2025-u-s-equities-year-in-review","open") | G8: Cboe FY25: "average daily notional value (ADNV) increasing 43.3% year-over-year to $1.1 trillion"
A9: US equity average daily volume | B9: 17.6 | C9: Bn shares | D9: VERIFIED | E9: S03 | F9: =HYPERLINK("https://www.cboe.com/insights/posts/2025-u-s-equities-year-in-review","open") | G9: Cboe FY25: "ADV increased 44.6% year-over-year to 17.6 billion shares"
A10: US trading days per year | B10: 251 | C10: days | D10: DERIVED | E10: S28 | F10: =HYPERLINK("https://www.nyse.com/markets/hours-calendars","open") | G10: 2026 has 261 weekdays less 10 full-day NYSE closures = 251
A11: US equity market cap, 4Q25 (turnover denominator) | B11: 69000 | C11: $Bn | D11: DERIVED | E11: S02 | F11: =HYPERLINK("https://www.sifma.org/research/statistics/research-quarterly-equity-and-related","open") | G11: SIFMA reported 1Q26 market cap of $66.0T at -4.3% Q/Q, which implies $69.0T at 4Q25. Matched to the FY25 ADV above so turnover is like-for-like
A12: Implied US equity turnover | B12: =B8*B10/B11 | C12: x mkt cap | D12: DERIVED | G12: ADV x trading days / market cap. v6.1 asserted 2.5x, which contradicted its own ADV input.
A14: 2. SEGMENTATION - RUSSELL INDEX BASIS
A15: The Russell 1000 boundary is the regulatory perimeter: the SEC's no-action letter scopes DTCC's tokenization service to the Russell 1000, index ETFs and Treasuries.
A16: Input | B16: Value | C16: Unit | D16: Status | E16: Src | F16: Link | G16: Basis / derivation
A17: Russell 3000 market cap | B17: 75600 | C17: $Bn | D17: VERIFIED | E17: S04 | F17: =HYPERLINK("https://www.lseg.com/en/insights/ftse-russell/russell-reconstitution-june-2026-larger-leaders-stronger-small-caps","open") | G17: LSEG June 2026 reconstitution: "$75.6 trillion on this year's rank day (April 30, 2026)"; ~98% of investable US market cap
A18: Russell 2000 market cap [Segment 2] | B18: 3500 | C18: $Bn | D18: VERIFIED | E18: S04 | F18: =HYPERLINK("https://www.lseg.com/en/insights/ftse-russell/russell-reconstitution-june-2026-larger-leaders-stronger-small-caps","open") | G18: LSEG June 2026 reconstitution: "$3.5 trillion in 2026"
A19: Russell 1000 market cap [Segment 1] | B19: =B17-B18 | C19: $Bn | D19: DERIVED | E19: S04 | F19: =HYPERLINK("https://www.lseg.com/en/insights/ftse-russell/russell-reconstitution-june-2026-larger-leaders-stronger-small-caps","open") | G19: Russell 3000 less Russell 2000
A20: Other US listed, outside Russell 3000 [Segment 3] | B20: =B6-B17 | C20: $Bn | D20: DERIVED | E20: S01 | F20: =HYPERLINK("https://www.sifma.org/wp-content/uploads/2026/04/SIFMA-Research-Quarterly-Equity-and-Related-2Q26.pdf","open") | G20: SIFMA total less Russell 3000. Note the two are struck 61 days apart (30-Apr-26 rank day vs 30-Jun-26 quarter end); the residual is small and the timing gap is disclosed rather than smoothed.
A21: Companies - Russell 1000 | B21: 1000 | C21: count | D21: VERIFIED | E21: S04 | F21: =HYPERLINK("https://www.lseg.com/en/insights/ftse-russell/russell-reconstitution-june-2026-larger-leaders-stronger-small-caps","open") | G21: Index construction: the 1,000 largest US companies by market cap
A22: Companies - Russell 2000 | B22: 2000 | C22: count | D22: VERIFIED | E22: S04 | F22: =HYPERLINK("https://www.lseg.com/en/insights/ftse-russell/russell-reconstitution-june-2026-larger-leaders-stronger-small-caps","open") | G22: Index construction: constituents 1,001-3,000
A23: Companies - other listed | B23: =B7-B21-B22 | C23: count | D23: DERIVED
A24: Russell 1000 / 2000 market cap breakpoint | B24: 5.7 | C24: $Bn | D24: VERIFIED | E24: S04 | F24: =HYPERLINK("https://www.lseg.com/en/insights/ftse-russell/russell-reconstitution-june-2026-larger-leaders-stronger-small-caps","open") | G24: LSEG June 2026 reconstitution: "$5.7 billion in 2026" (up from $4.6bn in 2025)
A26: 3. OBSERVED TOKENIZED EQUITY BASE - THE MODEL ANCHOR
A27: Input | B27: Value | C27: Unit | D27: Status | E27: Src | F27: Link | G27: Basis / derivation
A28: Tokenized equities, on-chain value | B28: 2.8 | C28: $Bn | D28: VERIFIED | E28: S07 | F28: =HYPERLINK("https://www.cryptotimes.io/2026/08/27/tokenized-rwa-market-hits-44-7b-as-funds-hold-76-4-share/","open") | G28: Token Terminal via Crypto Times, 26-Aug-26: tokenized stocks $2.8bn, 6.3% of a $44.7bn RWA market
A29: Cross-check - independent estimate | B29: 2.5 | C29: $Bn | D29: VERIFIED | E29: S08 | F29: =HYPERLINK("https://cryptobriefing.com/tokenized-stocks-rwa-market-cap-share/","open") | G29: rwa.xyz via Crypto Briefing, 13-Aug-26: ~$2.5bn distributed value, ~1.18m holders. Two providers 13 days apart agree within 12%
A30: Share of the observed base in Russell 1000 names | B30: 1 | C30: % | D30: VERIFIED | E30: S09 | F30: =HYPERLINK("https://www.webopedia.com/crypto/learn/biggest-tokenized-stocks/","open") | G30: All ten largest tokenized stocks are Russell 1000 constituents or index ETFs: TSLA, GOOGL, NVDA, CRCL, QQQ, SPY, MSTR, AAPL, COIN, GLD
A31: Anchor penetration, Russell 1000, 2026 | B31: =B28*B30/B19 | C31: % of seg | D31: DERIVED | G31: The adoption curve is forced through this point. It is an observation, not a choice.
A33: 4. PENETRATION ENGINE CONTROLS
A34: Sourced reference points that bracket the terminal ceiling. The ADR wrapper is the low outcome; the domestic equity ETF wrapper is the high outcome.
A35: Input | B35: Value | C35: Unit | D35: Status | E35: Src | F35: Link | G35: Basis / derivation
A36: REFERENCE - domestic equity ETF net assets / US market cap | B36: =10090.4/B6 | C36: % | D36: DERIVED | E36: S10 | F36: =HYPERLINK("https://www.ici.org/research/stats/etf/etfs_04_26","open") | G36: ICI Jul-26: domestic equity ETFs $10,090.4bn. Note the correct numerator - total ETF assets of $15.67T include bond, commodity and international funds and do not measure US equity penetration
A37: REFERENCE - DR value held / US market cap | B37: =1200/B6 | C37: % | D37: DERIVED | E37: S13 | F37: =HYPERLINK("https://www.bny.com/assets/corporate/documents/pdf/year-In-review-v8.pdf","open") | G37: BNY DR Market Review 2025: global DR investment $1.2T at YE25 across 2,885 programs
A38: Terminal penetration ceiling - Russell 1000 | B38: 0.08 | C38: % | D38: FORECAST | G38: Set between the two sourced references above. Russell 1000 leads because it is the only segment inside the DTCC no-action perimeter
A39: Terminal penetration ceiling - Russell 2000 | B39: 0.05 | C39: % | D39: FORECAST | G39: Below the Russell 1000 ceiling: outside the current perimeter and structurally less attractive to global retail demand
A40: Terminal penetration ceiling - other listed | B40: 0.02 | C40: % | D40: FORECAST | G40: ADR-like outcome. Micro caps lack the liquidity that makes a 24/7 wrapper worth issuing
A41: Logistic steepness k | B41: 0.9 | C41: - | D41: FORECAST | G41: Higher k = faster S-curve. At k=0.9 the Russell 1000 curve inflects in 2034 (see Penetration tab). Sensitivity on the Scenarios tab
A42: Adoption lag - Russell 2000 | B42: 3 | C42: years | D42: FORECAST | G42: Extending DTCC's service beyond the Russell 1000 requires fresh SEC relief; the current letter runs three years from 11-Dec-25
A43: Adoption lag - other listed | B43: 6 | C43: years | D43: FORECAST | G43: Two further relief cycles
A44: US equity market cap growth p.a. | B44: 0.05 | C44: % | D44: FORECAST | G44: Long-run nominal equity market growth. Applied uniformly to all three segments
A46: 5. REVENUE RATE ANCHORS - ALL COMPUTED FROM DISCLOSED FIGURES
A47: Input | B47: Value | C47: Unit | D47: Status | E47: Src | F47: Link | G47: Basis / derivation
A48: Retail equity take rate [trading anchor - low] | B48: =94/710000*10000 | C48: bps | D48: DERIVED | E48: S17 | F48: =HYPERLINK("https://investors.robinhood.com/node/15161/pdf","open") | G48: Robinhood Q4'25: equities transaction revenue $94m on equity notional volume $710bn
A49: Institutional crypto spot take rate [trading anchor - high] | B49: =185/215000*10000 | C49: bps | D49: DERIVED | E49: S16 | F49: =HYPERLINK("https://www.sec.gov/Archives/edgar/data/1679788/000167978826000011/q425shareholderletter.htm","open") | G49: Coinbase Q4'25: institutional transaction revenue $185m on institutional spot volume $215bn
A50: reference: consumer crypto spot take rate | B50: =734/56000*10000 | C50: bps | D50: DERIVED | E50: S16 | F50: =HYPERLINK("https://www.sec.gov/Archives/edgar/data/1679788/000167978826000011/q425shareholderletter.htm","open") | G50: Coinbase Q4'25: consumer revenue $734m on consumer spot volume $56bn. Outer bound - crypto retail fee conventions, ~100x equity conventions
A51: reference: Coinbase blended take rate FY25 | B51: =4055.4/5200000*10000 | C51: bps | D51: DERIVED | E51: S16 | F51: =HYPERLINK("https://www.sec.gov/Archives/edgar/data/1679788/000167978826000011/q425shareholderletter.htm","open") | G51: FY25 transaction revenue $4,055.4m on $5.2T total trading volume
A52: reference: exchange venue net capture | B52: =(0.018/100)/(B8/B9)*10000 | C52: bps | D52: DERIVED | E52: S18 | F52: =HYPERLINK("https://ir.cboe.com/news/news-details/2026/Cboe-Global-Markets-Reports-Results-for-Fourth-Quarter-2025-and-Full-Year/default.aspx","open") | G52: Cboe Q4'25 on-exchange net capture $0.018 per 100 touched shares, over an implied $62.50 average share price. The venue-only floor
A53: Securities lending utilisation | B53: =3250/46700 | C53: % | D53: DERIVED | E53: S14 | F53: =HYPERLINK("https://www.securitiesfinancetimes.com/securitieslendingnews/industryarticle.php?article_id=228388","open") | G53: S&P Global FY25: average on-loan $3.25T over average lendable $46.7T
A54: Securities lending average fee | B54: =14900/3250000*10000 | C54: bps | D54: DERIVED | E54: S14 | F54: =HYPERLINK("https://www.securitiesfinancetimes.com/securitieslendingnews/industryarticle.php?article_id=228388","open") | G54: S&P Global FY25: revenue $14.9bn over average on-loan balance $3.25T. EquiLend independently reports $15.3bn on balances above $4T
A55: Traditional custody fee yield | B55: =10211/59300000*10000 | C55: bps | D55: DERIVED | E55: S19 | F55: =HYPERLINK("https://www.bny.com/assets/corporate/documents/pdf/investor-relations/earnings/earnings-press-release-4q-2025.pdf","open") | G55: BNY FY25: investment services fees $10,211m over AUC/A of $59.3T. Coinbase no longer discloses custodial fee revenue separately, so a digital-native rate is not derivable
A56: Market data as % of trading revenue | B56: =1031/3885 | C56: % | D56: DERIVED | E56: S20 | F56: =HYPERLINK("https://ir.theice.com/press/news-details/2026/Intercontinental-Exchange-Reports-Strong-Full-Year-2025-Results/default.aspx","open") | G56: ICE FY25 Exchanges segment: data and connectivity $1,031m over transaction revenue net $3,885m
A57: reference: Nasdaq data + index over net market services | B57: =(804+827)/1201 | C57: % | D57: DERIVED | E57: S21 | F57: =HYPERLINK("https://ir.nasdaq.com/node/109901/pdf","open") | G57: Nasdaq FY25: Data and Listing $804m plus Index $827m over Market Services net $1,201m. Upper bound - Nasdaq's index franchise is not volume-linked
A58: NSCC value-into-net clearing fee | B58: 0.44 | C58: $/$M | D58: VERIFIED | E58: S23 | F58: =HYPERLINK("https://www.federalregister.gov/documents/2025/12/17/2025-23068/self-regulatory-organizations-national-securities-clearing-corporation-notice-of-filing-and","open") | G58: SR-NSCC-2025-017: "decrease its 'value into the net' fee from $0.46 to $0.44 per million of processed value", implemented 01-Jan-2026. The published fee guide PDF retrieved 10-Sep-2026 still shows 0.46, so the rule filing is the authority
A59: NSCC clearing fee in bps | B59: =B58/1000000*10000 | C59: bps | D59: DERIVED | E59: S23 | F59: =HYPERLINK("https://www.federalregister.gov/documents/2025/12/17/2025-23068/self-regulatory-organizations-national-securities-clearing-corporation-notice-of-filing-and","open") | G59: Converted to bps on notional. v6.1 modelled $0.10 per trade against this same source, overstating clearing revenue by roughly 20-45x depending on trade size
A60: UPPER BOOKEND - full-service tokenization yield, Q1'26 | B60: =19.5*4/3200*10000 | C60: bps | D60: DERIVED | E60: S25 | F60: =HYPERLINK("https://www.prnewswire.com/news-releases/securitize-reports-first-quarter-2026-results-302777848.html","open") | G60: Securitize Q1'26: revenue $19.5m annualised over average tokenized AUM $3.2bn
A61: UPPER BOOKEND - full-service tokenization yield, Q2'26 | B61: =14.4*4/4300*10000 | C61: bps | D61: DERIVED | E61: S24 | F61: =HYPERLINK("https://www.prnewswire.com/news-releases/securitize-reports-second-quarter-2026-results-302850119.html","open") | G61: Securitize Q2'26: revenue $14.4m annualised over average tokenized AUM $4.3bn. Yield nearly halved in one quarter as AUM scaled - observed compression, not an assumed one. This is fund tokenization: the security is created, administered and transfer-agented by one provider
A62: LOWER BOOKEND - utility servicing yield on listed securities | B62: =664.551/100300000*10000 | C62: bps | D62: DERIVED | E62: S31 | F62: =HYPERLINK("https://www.dtcc.com/-/media/Files/Downloads/legal/financials/2025/DTCC-Annual-Financial-Statement-2025.pdf","open") | G62: DTCC FY25 settlement and asset services revenue $664.6m over DTC assets under custody of $100.3T (S32). This is what it costs to service a listed security that already exists - the tokenized wrapper is incremental to this, not a replacement for it
A64: 6. MIX DRIVERS - STRAIGHT-LINE 2026 TO 2035
A65: These are forecasts. Each is bracketed by the sourced anchors above and each is listed on the Audit tab.
A66: Driver | B66: 2026 | C66: 2035 | D66: Status | E66: Src | F66: Link | G66: Basis
A67: Share of tokenized volume on crypto-venue fee terms | B67: 0.9 | C67: 0.3 | D67: FORECAST | G67: Blends the two trading anchors. Today's tokenized equity volume sits almost entirely on crypto venues; DTCC's onshore rail pulls it toward equity fee conventions
A68: Tokenized turnover as % of US equity turnover | B68: 0.2 | C68: 1 | D68: FORECAST | G68: Tokenized names trade thinner than their underlyings today, converging as the wrapper matures and 24/7 access adds sessions
A69: Lendable share of tokenized market cap | B69: 0.3 | C69: 0.8 | D69: FORECAST | G69: Applied to the sourced 6.96% utilisation. Tokenized holdings are held in programmable custody, so a higher share is lending-enabled than in the traditional market
A70: Share of tokenized market cap in institutional custody | B70: 0.3 | C70: 0.65 | D70: FORECAST | G70: The DTCC rail is institution-facing by construction; the offshore rails are retail-facing
A71: Digital custody fee premium over BNY rate | B71: 6 | C71: 2 | D71: FORECAST | G71: Digital-asset custody prices above traditional custody today and compresses toward it. Applied to the disclosed 1.72bps BNY yield
A72: Tokenization + servicing yield applied (bps) | B72: 20 | C72: 5 | D72: FORECAST | G72: Sits between the two sourced bookends above: DTCC's 0.066bps utility rate for servicing an already-listed security, and Securitize's 134bps full-service fund tokenization rate. Set near the low end because a tokenized listed equity is a wrapper on a security that is already issued, custodied and transfer-agented - and because no tokenized equity platform currently publishes an explicit servicing fee. Ondo, the largest at over $1bn TVL across 440+ listings, discloses none and monetises through spread, which this model already captures in pool 1

Sheet Penetration
A1: Penetration Engine
A2: Logistic adoption curve forced through the observed 2026 on-chain base. Type into the override rows to impose your own path; blank cells keep the curve.
A4: CURVE FORM
A5: P(t) = L / (1 + EXP(-k(t - t0))). L is the terminal ceiling, k the steepness, t0 the inflection year. t0 is not an input: it is solved so that the curve passes exactly through the observed 2026 penetration. t0 = 2026 + LN(L/P0 - 1)/k.
A7: Observed 2026 penetration, Russell 1000 (P0) | B7: =Inputs!B31
A8: Solved inflection year, Russell 1000 (t0) | B8: =2026+LN(Inputs!B38/B7-1)/Inputs!B41
A10: MODELLED PENETRATION (% OF SEGMENT MARKET CAP)
A11: Segment | B11: Ceiling / lag | C11: 2026 | D11: 2027 | E11: 2028 | F11: 2029 | G11: 2030 | H11: 2031 | I11: 2032 | J11: 2033 | K11: 2034 | L11: 2035
A12: Russell 1000 | B12: =Inputs!B38 | C12: =Inputs!$B$38/(1+EXP(-Inputs!$B$41*(2026-$B$8))) | D12: =Inputs!$B$38/(1+EXP(-Inputs!$B$41*(2027-$B$8))) | E12: =Inputs!$B$38/(1+EXP(-Inputs!$B$41*(2028-$B$8))) | F12: =Inputs!$B$38/(1+EXP(-Inputs!$B$41*(2029-$B$8))) | G12: =Inputs!$B$38/(1+EXP(-Inputs!$B$41*(2030-$B$8))) | H12: =Inputs!$B$38/(1+EXP(-Inputs!$B$41*(2031-$B$8))) | I12: =Inputs!$B$38/(1+EXP(-Inputs!$B$41*(2032-$B$8))) | J12: =Inputs!$B$38/(1+EXP(-Inputs!$B$41*(2033-$B$8))) | K12: =Inputs!$B$38/(1+EXP(-Inputs!$B$41*(2034-$B$8))) | L12: =Inputs!$B$38/(1+EXP(-Inputs!$B$41*(2035-$B$8)))
A13: Russell 2000 | B13: =Inputs!B39 | C13: =Inputs!$B$39/(1+EXP(-Inputs!$B$41*(2026-$B$8-Inputs!$B$42))) | D13: =Inputs!$B$39/(1+EXP(-Inputs!$B$41*(2027-$B$8-Inputs!$B$42))) | E13: =Inputs!$B$39/(1+EXP(-Inputs!$B$41*(2028-$B$8-Inputs!$B$42))) | F13: =Inputs!$B$39/(1+EXP(-Inputs!$B$41*(2029-$B$8-Inputs!$B$42))) | G13: =Inputs!$B$39/(1+EXP(-Inputs!$B$41*(2030-$B$8-Inputs!$B$42))) | H13: =Inputs!$B$39/(1+EXP(-Inputs!$B$41*(2031-$B$8-Inputs!$B$42))) | I13: =Inputs!$B$39/(1+EXP(-Inputs!$B$41*(2032-$B$8-Inputs!$B$42))) | J13: =Inputs!$B$39/(1+EXP(-Inputs!$B$41*(2033-$B$8-Inputs!$B$42))) | K13: =Inputs!$B$39/(1+EXP(-Inputs!$B$41*(2034-$B$8-Inputs!$B$42))) | L13: =Inputs!$B$39/(1+EXP(-Inputs!$B$41*(2035-$B$8-Inputs!$B$42)))
A14: Other listed | B14: =Inputs!B40 | C14: =Inputs!$B$40/(1+EXP(-Inputs!$B$41*(2026-$B$8-Inputs!$B$43))) | D14: =Inputs!$B$40/(1+EXP(-Inputs!$B$41*(2027-$B$8-Inputs!$B$43))) | E14: =Inputs!$B$40/(1+EXP(-Inputs!$B$41*(2028-$B$8-Inputs!$B$43))) | F14: =Inputs!$B$40/(1+EXP(-Inputs!$B$41*(2029-$B$8-Inputs!$B$43))) | G14: =Inputs!$B$40/(1+EXP(-Inputs!$B$41*(2030-$B$8-Inputs!$B$43))) | H14: =Inputs!$B$40/(1+EXP(-Inputs!$B$41*(2031-$B$8-Inputs!$B$43))) | I14: =Inputs!$B$40/(1+EXP(-Inputs!$B$41*(2032-$B$8-Inputs!$B$43))) | J14: =Inputs!$B$40/(1+EXP(-Inputs!$B$41*(2033-$B$8-Inputs!$B$43))) | K14: =Inputs!$B$40/(1+EXP(-Inputs!$B$41*(2034-$B$8-Inputs!$B$43))) | L14: =Inputs!$B$40/(1+EXP(-Inputs!$B$41*(2035-$B$8-Inputs!$B$43)))
A16: OVERRIDE - TYPE A PENETRATION RATE HERE TO REPLACE THE CURVE
A17: Any cell you fill overrides the modelled curve for that segment and year. Leave blank to keep the curve.
A18: Russell 1000 override
A19: Russell 2000 override
A20: Other listed override
A22: ACTIVE PENETRATION - USED BY THE PROJECTION
A23: Russell 1000 | C23: =IF(C18="",C12,C18) | D23: =IF(D18="",D12,D18) | E23: =IF(E18="",E12,E18) | F23: =IF(F18="",F12,F18) | G23: =IF(G18="",G12,G18) | H23: =IF(H18="",H12,H18) | I23: =IF(I18="",I12,I18) | J23: =IF(J18="",J12,J18) | ... L23: =IF(L18="",L12,L18)
A24: Russell 2000 | C24: =IF(C19="",C13,C19) | D24: =IF(D19="",D13,D19) | E24: =IF(E19="",E13,E19) | F24: =IF(F19="",F13,F19) | G24: =IF(G19="",G13,G19) | H24: =IF(H19="",H13,H19) | I24: =IF(I19="",I13,I19) | J24: =IF(J19="",J13,J19) | ... L24: =IF(L19="",L13,L19)
A25: Other listed | C25: =IF(C20="",C14,C20) | D25: =IF(D20="",D14,D20) | E25: =IF(E20="",E14,E20) | F25: =IF(F20="",F14,F20) | G25: =IF(G20="",G14,G20) | H25: =IF(H20="",H14,H20) | I25: =IF(I20="",I14,I20) | J25: =IF(J20="",J14,J20) | ... L25: =IF(L20="",L14,L20)
A27: Overrides active | C27: =COUNTIF(C18:C20,"<>") | D27: =COUNTIF(D18:D20,"<>") | E27: =COUNTIF(E18:E20,"<>") | F27: =COUNTIF(F18:F20,"<>") | G27: =COUNTIF(G18:G20,"<>") | H27: =COUNTIF(H18:H20,"<>") | I27: =COUNTIF(I18:I20,"<>") | J27: =COUNTIF(J18:J20,"<>") | ... L27: =COUNTIF(L18:L20,"<>")

Sheet Projection
A1: Projection
A2: Tokenized US equity market capitalisation by segment, $Bn
A4: SEGMENT MARKET CAP ($Bn)
C5: 2026 | D5: 2027 | E5: 2028 | F5: 2029 | G5: 2030 | H5: 2031 | I5: 2032 | J5: 2033 | K5: 2034 | L5: 2035
A6: Russell 1000 | C6: =Inputs!B19 | D6: =C6*(1+Inputs!B44) | E6: =D6*(1+Inputs!B44) | F6: =E6*(1+Inputs!B44) | G6: =F6*(1+Inputs!B44) | H6: =G6*(1+Inputs!B44) | I6: =H6*(1+Inputs!B44) | J6: =I6*(1+Inputs!B44) | K6: =J6*(1+Inputs!B44) | L6: =K6*(1+Inputs!B44)
A7: Russell 2000 | C7: =Inputs!B18 | D7: =C7*(1+Inputs!B44) | E7: =D7*(1+Inputs!B44) | F7: =E7*(1+Inputs!B44) | G7: =F7*(1+Inputs!B44) | H7: =G7*(1+Inputs!B44) | I7: =H7*(1+Inputs!B44) | J7: =I7*(1+Inputs!B44) | K7: =J7*(1+Inputs!B44) | L7: =K7*(1+Inputs!B44)
A8: Other listed | C8: =Inputs!B20 | D8: =C8*(1+Inputs!B44) | E8: =D8*(1+Inputs!B44) | F8: =E8*(1+Inputs!B44) | G8: =F8*(1+Inputs!B44) | H8: =G8*(1+Inputs!B44) | I8: =H8*(1+Inputs!B44) | J8: =I8*(1+Inputs!B44) | K8: =J8*(1+Inputs!B44) | L8: =K8*(1+Inputs!B44)
A9: Total US equity market cap | C9: =SUM(C6:C8) | D9: =SUM(D6:D8) | E9: =SUM(E6:E8) | F9: =SUM(F6:F8) | G9: =SUM(G6:G8) | H9: =SUM(H6:H8) | I9: =SUM(I6:I8) | J9: =SUM(J6:J8) | ... L9: =SUM(L6:L8)
A11: PENETRATION (% OF SEGMENT MARKET CAP)
C12: 2026 | D12: 2027 | E12: 2028 | F12: 2029 | G12: 2030 | H12: 2031 | I12: 2032 | J12: 2033 | K12: 2034 | L12: 2035
A13: Russell 1000 | C13: =Penetration!C23 | D13: =Penetration!D23 | E13: =Penetration!E23 | F13: =Penetration!F23 | G13: =Penetration!G23 | H13: =Penetration!H23 | I13: =Penetration!I23 | J13: =Penetration!J23 | ... L13: =Penetration!L23
A14: Russell 2000 | C14: =Penetration!C24 | D14: =Penetration!D24 | E14: =Penetration!E24 | F14: =Penetration!F24 | G14: =Penetration!G24 | H14: =Penetration!H24 | I14: =Penetration!I24 | J14: =Penetration!J24 | ... L14: =Penetration!L24
A15: Other listed | C15: =Penetration!C25 | D15: =Penetration!D25 | E15: =Penetration!E25 | F15: =Penetration!F25 | G15: =Penetration!G25 | H15: =Penetration!H25 | I15: =Penetration!I25 | J15: =Penetration!J25 | ... L15: =Penetration!L25
A17: TOKENIZED MARKET CAP ($Bn)
C18: 2026 | D18: 2027 | E18: 2028 | F18: 2029 | G18: 2030 | H18: 2031 | I18: 2032 | J18: 2033 | K18: 2034 | L18: 2035
A19: Russell 1000 | C19: =C6*C13 | D19: =D6*D13 | E19: =E6*E13 | F19: =F6*F13 | G19: =G6*G13 | H19: =H6*H13 | I19: =I6*I13 | J19: =J6*J13 | ... L19: =L6*L13
A20: Russell 2000 | C20: =C7*C14 | D20: =D7*D14 | E20: =E7*E14 | F20: =F7*F14 | G20: =G7*G14 | H20: =H7*H14 | I20: =I7*I14 | J20: =J7*J14 | ... L20: =L7*L14
A21: Other listed | C21: =C8*C15 | D21: =D8*D15 | E21: =E8*E15 | F21: =F8*F15 | G21: =G8*G15 | H21: =H8*H15 | I21: =I8*I15 | J21: =J8*J15 | ... L21: =L8*L15
A22: Total tokenized equity market cap | C22: =SUM(C19:C21) | D22: =SUM(D19:D21) | E22: =SUM(E19:E21) | F22: =SUM(F19:F21) | G22: =SUM(G19:G21) | H22: =SUM(H19:H21) | I22: =SUM(I19:I21) | J22: =SUM(J19:J21) | ... L22: =SUM(L19:L21)
A23: Blended penetration of US market cap | C23: =C22/C9 | D23: =D22/D9 | E23: =E22/E9 | F23: =F22/F9 | G23: =G22/G9 | H23: =H22/H9 | I23: =I22/I9 | J23: =J22/J9 | ... L23: =L22/L9
A24: Y/Y growth in tokenized market cap | D24: =D22/C22-1 | E24: =E22/D22-1 | F24: =F22/E22-1 | G24: =G22/F22-1 | H24: =H22/G22-1 | I24: =I22/H22-1 | J24: =J22/I22-1 | K24: =K22/J22-1 | L24: =L22/K22-1
A26: SEGMENT CONTRIBUTION (% OF TOKENIZED TOTAL)
C27: 2026 | D27: 2027 | E27: 2028 | F27: 2029 | G27: 2030 | H27: 2031 | I27: 2032 | J27: 2033 | K27: 2034 | L27: 2035
A28: Russell 1000 | C28: =IFERROR(C19/C22,0) | D28: =IFERROR(D19/D22,0) | E28: =IFERROR(E19/E22,0) | F28: =IFERROR(F19/F22,0) | G28: =IFERROR(G19/G22,0) | H28: =IFERROR(H19/H22,0) | I28: =IFERROR(I19/I22,0) | J28: =IFERROR(J19/J22,0) | ... L28: =IFERROR(L19/L22,0)
A29: Russell 2000 | C29: =IFERROR(C20/C22,0) | D29: =IFERROR(D20/D22,0) | E29: =IFERROR(E20/E22,0) | F29: =IFERROR(F20/F22,0) | G29: =IFERROR(G20/G22,0) | H29: =IFERROR(H20/H22,0) | I29: =IFERROR(I20/I22,0) | J29: =IFERROR(J20/J22,0) | ... L29: =IFERROR(L20/L22,0)
A30: Other listed | C30: =IFERROR(C21/C22,0) | D30: =IFERROR(D21/D22,0) | E30: =IFERROR(E21/E22,0) | F30: =IFERROR(F21/F22,0) | G30: =IFERROR(G21/G22,0) | H30: =IFERROR(H21/H22,0) | I30: =IFERROR(I21/I22,0) | J30: =IFERROR(J21/J22,0) | ... L30: =IFERROR(L21/L22,0)
A32: COVERAGE IDENTITY - HOW THE PENETRATION RATE DECOMPOSES
A33: Tokenization does not convert whole companies; it tokenizes a slice of a name's float. Penetration is therefore the product of how many names participate and how much of each one's float is tokenized. v6.1 multiplied a market-cap penetration rate by a company count, which silently treats every tokenized name as fully converted and produces an issuer count that cannot be right. The identity below is exact arithmetic: for a given number of participating Russell 1000 names, it reports the tokenized share of each participating name's float that the projection implies.
C34: 2026 | D34: 2027 | E34: 2028 | F34: 2029 | G34: 2030 | H34: 2031 | I34: 2032 | J34: 2033 | K34: 2034 | L34: 2035
A35: If 100 Russell 1000 names participate, tokenized share of each name's float | C35: =C13*Inputs!$B$21/100 | D35: =D13*Inputs!$B$21/100 | E35: =E13*Inputs!$B$21/100 | F35: =F13*Inputs!$B$21/100 | G35: =G13*Inputs!$B$21/100 | H35: =H13*Inputs!$B$21/100 | I35: =I13*Inputs!$B$21/100 | J35: =J13*Inputs!$B$21/100 | ... L35: =L13*Inputs!$B$21/100
A36: If 250 Russell 1000 names participate, tokenized share of each name's float | C36: =C13*Inputs!$B$21/250 | D36: =D13*Inputs!$B$21/250 | E36: =E13*Inputs!$B$21/250 | F36: =F13*Inputs!$B$21/250 | G36: =G13*Inputs!$B$21/250 | H36: =H13*Inputs!$B$21/250 | I36: =I13*Inputs!$B$21/250 | J36: =J13*Inputs!$B$21/250 | ... L36: =L13*Inputs!$B$21/250
A37: If 500 Russell 1000 names participate, tokenized share of each name's float | C37: =C13*Inputs!$B$21/500 | D37: =D13*Inputs!$B$21/500 | E37: =E13*Inputs!$B$21/500 | F37: =F13*Inputs!$B$21/500 | G37: =G13*Inputs!$B$21/500 | H37: =H13*Inputs!$B$21/500 | I37: =I13*Inputs!$B$21/500 | J37: =J13*Inputs!$B$21/500 | ... L37: =L13*Inputs!$B$21/500
A38: If 1,000 Russell 1000 names participate, tokenized share of each name's float | C38: =C13*Inputs!$B$21/1000 | D38: =D13*Inputs!$B$21/1000 | E38: =E13*Inputs!$B$21/1000 | F38: =F13*Inputs!$B$21/1000 | G38: =G13*Inputs!$B$21/1000 | H38: =H13*Inputs!$B$21/1000 | I38: =I13*Inputs!$B$21/1000 | J38: =J13*Inputs!$B$21/1000 | ... L38: =L13*Inputs!$B$21/1000
A39: Reference: observed today - Tesla token / Tesla market cap | C39: 5e-05 | D39: TSLAx at roughly $71m against Tesla's market cap (S09). Consistent with several hundred participating names at today's penetration.

Sheet Revenue Pools
A1: Revenue Pools
A2: Annual revenue available to the tokenized US equity ecosystem, $M. Every rate traces to a disclosed figure on the Inputs tab.
A4: INPUT FROM PROJECTION
C5: 2026 | D5: 2027 | E5: 2028 | F5: 2029 | G5: 2030 | H5: 2031 | I5: 2032 | J5: 2033 | K5: 2034 | L5: 2035
A6: Tokenized equity market cap ($M) | C6: =Projection!C22*1000 | D6: =Projection!D22*1000 | E6: =Projection!E22*1000 | F6: =Projection!F22*1000 | G6: =Projection!G22*1000 | H6: =Projection!H22*1000 | I6: =Projection!I22*1000 | J6: =Projection!J22*1000 | ... L6: =Projection!L22*1000
A8: 1. TRADING
C9: 2026 | D9: 2027 | E9: 2028 | F9: 2029 | G9: 2030 | H9: 2031 | I9: 2032 | J9: 2033 | K9: 2034 | L9: 2035
A10: Tokenized turnover (x market cap) | C10: =Inputs!$B$12*(Inputs!$B$68+(Inputs!$C$68-Inputs!$B$68)*0/9) | D10: =Inputs!$B$12*(Inputs!$B$68+(Inputs!$C$68-Inputs!$B$68)*1/9) | E10: =Inputs!$B$12*(Inputs!$B$68+(Inputs!$C$68-Inputs!$B$68)*2/9) | F10: =Inputs!$B$12*(Inputs!$B$68+(Inputs!$C$68-Inputs!$B$68)*3/9) | G10: =Inputs!$B$12*(Inputs!$B$68+(Inputs!$C$68-Inputs!$B$68)*4/9) | H10: =Inputs!$B$12*(Inputs!$B$68+(Inputs!$C$68-Inputs!$B$68)*5/9) | I10: =Inputs!$B$12*(Inputs!$B$68+(Inputs!$C$68-Inputs!$B$68)*6/9) | J10: =Inputs!$B$12*(Inputs!$B$68+(Inputs!$C$68-Inputs!$B$68)*7/9) | K10: =Inputs!$B$12*(Inputs!$B$68+(Inputs!$C$68-Inputs!$B$68)*8/9) | L10: =Inputs!$B$12*(Inputs!$B$68+(Inputs!$C$68-Inputs!$B$68)*9/9) | M10: S03 | N10: =HYPERLINK("https://www.cboe.com/insights/posts/2025-u-s-equities-year-in-review","src")
A11: Trading volume ($M) | C11: =C6*C10 | D11: =D6*D10 | E11: =E6*E10 | F11: =F6*F10 | G11: =G6*G10 | H11: =H6*H10 | I11: =I6*I10 | J11: =J6*J10 | ... L11: =L6*L10
A12: Blended take rate (bps) | C12: =(Inputs!$B$67+(Inputs!$C$67-Inputs!$B$67)*0/9)*Inputs!$B$49+(1-(Inputs!$B$67+(Inputs!$C$67-Inputs!$B$67)*0/9))*Inputs!$B$48 | D12: =(Inputs!$B$67+(Inputs!$C$67-Inputs!$B$67)*1/9)*Inputs!$B$49+(1-(Inputs!$B$67+(Inputs!$C$67-Inputs!$B$67)*1/9))*Inputs!$B$48 | E12: =(Inputs!$B$67+(Inputs!$C$67-Inputs!$B$67)*2/9)*Inputs!$B$49+(1-(Inputs!$B$67+(Inputs!$C$67-Inputs!$B$67)*2/9))*Inputs!$B$48 | F12: =(Inputs!$B$67+(Inputs!$C$67-Inputs!$B$67)*3/9)*Inputs!$B$49+(1-(Inputs!$B$67+(Inputs!$C$67-Inputs!$B$67)*3/9))*Inputs!$B$48 | G12: =(Inputs!$B$67+(Inputs!$C$67-Inputs!$B$67)*4/9)*Inputs!$B$49+(1-(Inputs!$B$67+(Inputs!$C$67-Inputs!$B$67)*4/9))*Inputs!$B$48 | H12: =(Inputs!$B$67+(Inputs!$C$67-Inputs!$B$67)*5/9)*Inputs!$B$49+(1-(Inputs!$B$67+(Inputs!$C$67-Inputs!$B$67)*5/9))*Inputs!$B$48 | I12: =(Inputs!$B$67+(Inputs!$C$67-Inputs!$B$67)*6/9)*Inputs!$B$49+(1-(Inputs!$B$67+(Inputs!$C$67-Inputs!$B$67)*6/9))*Inputs!$B$48 | J12: =(Inputs!$B$67+(Inputs!$C$67-Inputs!$B$67)*7/9)*Inputs!$B$49+(1-(Inputs!$B$67+(Inputs!$C$67-Inputs!$B$67)*7/9))*Inputs!$B$48 | K12: =(Inputs!$B$67+(Inputs!$C$67-Inputs!$B$67)*8/9)*Inputs!$B$49+(1-(Inputs!$B$67+(Inputs!$C$67-Inputs!$B$67)*8/9))*Inputs!$B$48 | L12: =(Inputs!$B$67+(Inputs!$C$67-Inputs!$B$67)*9/9)*Inputs!$B$49+(1-(Inputs!$B$67+(Inputs!$C$67-Inputs!$B$67)*9/9))*Inputs!$B$48 | M12: S17 | N12: =HYPERLINK("https://investors.robinhood.com/node/15161/pdf","src")
A13: Trading revenue ($M) | C13: =C11*C12/10000 | D13: =D11*D12/10000 | E13: =E11*E12/10000 | F13: =F11*F12/10000 | G13: =G11*G12/10000 | H13: =H11*H12/10000 | I13: =I11*I12/10000 | J13: =J11*J12/10000 | ... L13: =L11*L12/10000
A15: 2. SECURITIES LENDING (GROSS POOL)
C16: 2026 | D16: 2027 | E16: 2028 | F16: 2029 | G16: 2030 | H16: 2031 | I16: 2032 | J16: 2033 | K16: 2034 | L16: 2035
A17: Lendable pool ($M) | C17: =C6*(Inputs!$B$69+(Inputs!$C$69-Inputs!$B$69)*0/9) | D17: =D6*(Inputs!$B$69+(Inputs!$C$69-Inputs!$B$69)*1/9) | E17: =E6*(Inputs!$B$69+(Inputs!$C$69-Inputs!$B$69)*2/9) | F17: =F6*(Inputs!$B$69+(Inputs!$C$69-Inputs!$B$69)*3/9) | G17: =G6*(Inputs!$B$69+(Inputs!$C$69-Inputs!$B$69)*4/9) | H17: =H6*(Inputs!$B$69+(Inputs!$C$69-Inputs!$B$69)*5/9) | I17: =I6*(Inputs!$B$69+(Inputs!$C$69-Inputs!$B$69)*6/9) | J17: =J6*(Inputs!$B$69+(Inputs!$C$69-Inputs!$B$69)*7/9) | K17: =K6*(Inputs!$B$69+(Inputs!$C$69-Inputs!$B$69)*8/9) | L17: =L6*(Inputs!$B$69+(Inputs!$C$69-Inputs!$B$69)*9/9)
A18: On-loan balance ($M) [at sourced 6.96% utilisation] | C18: =C17*Inputs!$B$53 | D18: =D17*Inputs!$B$53 | E18: =E17*Inputs!$B$53 | F18: =F17*Inputs!$B$53 | G18: =G17*Inputs!$B$53 | H18: =H17*Inputs!$B$53 | I18: =I17*Inputs!$B$53 | J18: =J17*Inputs!$B$53 | ... L18: =L17*Inputs!$B$53 | M18: S14 | N18: =HYPERLINK("https://www.securitiesfinancetimes.com/securitieslendingnews/industryarticle.php?article_id=228388","src")
A19: Securities lending revenue ($M) | C19: =C18*Inputs!$B$54/10000 | D19: =D18*Inputs!$B$54/10000 | E19: =E18*Inputs!$B$54/10000 | F19: =F18*Inputs!$B$54/10000 | G19: =G18*Inputs!$B$54/10000 | H19: =H18*Inputs!$B$54/10000 | I19: =I18*Inputs!$B$54/10000 | J19: =J18*Inputs!$B$54/10000 | ... L19: =L18*Inputs!$B$54/10000 | M19: S14 | N19: =HYPERLINK("https://www.securitiesfinancetimes.com/securitieslendingnews/industryarticle.php?article_id=228388","src")
A21: 3. CUSTODY AND PRIME
C22: 2026 | D22: 2027 | E22: 2028 | F22: 2029 | G22: 2030 | H22: 2031 | I22: 2032 | J22: 2033 | K22: 2034 | L22: 2035
A23: Assets under institutional custody ($M) | C23: =C6*(Inputs!$B$70+(Inputs!$C$70-Inputs!$B$70)*0/9) | D23: =D6*(Inputs!$B$70+(Inputs!$C$70-Inputs!$B$70)*1/9) | E23: =E6*(Inputs!$B$70+(Inputs!$C$70-Inputs!$B$70)*2/9) | F23: =F6*(Inputs!$B$70+(Inputs!$C$70-Inputs!$B$70)*3/9) | G23: =G6*(Inputs!$B$70+(Inputs!$C$70-Inputs!$B$70)*4/9) | H23: =H6*(Inputs!$B$70+(Inputs!$C$70-Inputs!$B$70)*5/9) | I23: =I6*(Inputs!$B$70+(Inputs!$C$70-Inputs!$B$70)*6/9) | J23: =J6*(Inputs!$B$70+(Inputs!$C$70-Inputs!$B$70)*7/9) | K23: =K6*(Inputs!$B$70+(Inputs!$C$70-Inputs!$B$70)*8/9) | L23: =L6*(Inputs!$B$70+(Inputs!$C$70-Inputs!$B$70)*9/9)
A24: Custody fee (bps on AUC) | C24: =Inputs!$B$55*(Inputs!$B$71+(Inputs!$C$71-Inputs!$B$71)*0/9) | D24: =Inputs!$B$55*(Inputs!$B$71+(Inputs!$C$71-Inputs!$B$71)*1/9) | E24: =Inputs!$B$55*(Inputs!$B$71+(Inputs!$C$71-Inputs!$B$71)*2/9) | F24: =Inputs!$B$55*(Inputs!$B$71+(Inputs!$C$71-Inputs!$B$71)*3/9) | G24: =Inputs!$B$55*(Inputs!$B$71+(Inputs!$C$71-Inputs!$B$71)*4/9) | H24: =Inputs!$B$55*(Inputs!$B$71+(Inputs!$C$71-Inputs!$B$71)*5/9) | I24: =Inputs!$B$55*(Inputs!$B$71+(Inputs!$C$71-Inputs!$B$71)*6/9) | J24: =Inputs!$B$55*(Inputs!$B$71+(Inputs!$C$71-Inputs!$B$71)*7/9) | K24: =Inputs!$B$55*(Inputs!$B$71+(Inputs!$C$71-Inputs!$B$71)*8/9) | L24: =Inputs!$B$55*(Inputs!$B$71+(Inputs!$C$71-Inputs!$B$71)*9/9) | M24: S19 | N24: =HYPERLINK("https://www.bny.com/assets/corporate/documents/pdf/investor-relations/earnings/earnings-press-release-4q-2025.pdf","src")
A25: Custody and prime revenue ($M) | C25: =C23*C24/10000 | D25: =D23*D24/10000 | E25: =E23*E24/10000 | F25: =F23*F24/10000 | G25: =G23*G24/10000 | H25: =H23*H24/10000 | I25: =I23*I24/10000 | J25: =J23*J24/10000 | ... L25: =L23*L24/10000
A27: 4. TOKENIZATION AND ASSET SERVICING
A28: Bracketed by two sourced yields on serviced assets. Lower bookend: DTCC settlement and asset services, 0.066bps on assets under custody - the utility rate for servicing a listed security that already exists. Upper bookend: Securitize, 134bps on tokenized AUM - full-service creation and administration of a tokenized fund. A tokenized listed equity is a wrapper on an already-serviced security, so the applied yield sits near the low end.
C29: 2026 | D29: 2027 | E29: 2028 | F29: 2029 | G29: 2030 | H29: 2031 | I29: 2032 | J29: 2033 | K29: 2034 | L29: 2035
A30: bookend - DTCC utility servicing yield (bps) | C30: =Inputs!$B$62 | D30: =Inputs!$B$62 | E30: =Inputs!$B$62 | F30: =Inputs!$B$62 | G30: =Inputs!$B$62 | H30: =Inputs!$B$62 | I30: =Inputs!$B$62 | J30: =Inputs!$B$62 | ... L30: =Inputs!$B$62 | M30: S31 | N30: =HYPERLINK("https://www.dtcc.com/-/media/Files/Downloads/legal/financials/2025/DTCC-Annual-Financial-Statement-2025.pdf","src")
A31: bookend - Securitize full-service yield (bps) | C31: =Inputs!$B$61 | D31: =Inputs!$B$61 | E31: =Inputs!$B$61 | F31: =Inputs!$B$61 | G31: =Inputs!$B$61 | H31: =Inputs!$B$61 | I31: =Inputs!$B$61 | J31: =Inputs!$B$61 | ... L31: =Inputs!$B$61 | M31: S24 | N31: =HYPERLINK("https://www.prnewswire.com/news-releases/securitize-reports-second-quarter-2026-results-302850119.html","src")
A32: Tokenization + servicing yield applied (bps) | C32: =(Inputs!$B$72+(Inputs!$C$72-Inputs!$B$72)*0/9) | D32: =(Inputs!$B$72+(Inputs!$C$72-Inputs!$B$72)*1/9) | E32: =(Inputs!$B$72+(Inputs!$C$72-Inputs!$B$72)*2/9) | F32: =(Inputs!$B$72+(Inputs!$C$72-Inputs!$B$72)*3/9) | G32: =(Inputs!$B$72+(Inputs!$C$72-Inputs!$B$72)*4/9) | H32: =(Inputs!$B$72+(Inputs!$C$72-Inputs!$B$72)*5/9) | I32: =(Inputs!$B$72+(Inputs!$C$72-Inputs!$B$72)*6/9) | J32: =(Inputs!$B$72+(Inputs!$C$72-Inputs!$B$72)*7/9) | K32: =(Inputs!$B$72+(Inputs!$C$72-Inputs!$B$72)*8/9) | L32: =(Inputs!$B$72+(Inputs!$C$72-Inputs!$B$72)*9/9)
A33: Tokenization + servicing revenue ($M) | C33: =C6*C32/10000 | D33: =D6*D32/10000 | E33: =E6*E32/10000 | F33: =F6*F32/10000 | G33: =G6*G32/10000 | H33: =H6*H32/10000 | I33: =I6*I32/10000 | J33: =J6*J32/10000 | ... L33: =L6*L32/10000
A35: 5. MARKET DATA AND INDEX LICENSING
C36: 2026 | D36: 2027 | E36: 2028 | F36: 2029 | G36: 2030 | H36: 2031 | I36: 2032 | J36: 2033 | K36: 2034 | L36: 2035
A37: Market data revenue ($M) [26.5% of trading revenue, ICE basis] | C37: =C13*Inputs!$B$56 | D37: =D13*Inputs!$B$56 | E37: =E13*Inputs!$B$56 | F37: =F13*Inputs!$B$56 | G37: =G13*Inputs!$B$56 | H37: =H13*Inputs!$B$56 | I37: =I13*Inputs!$B$56 | J37: =J13*Inputs!$B$56 | ... L37: =L13*Inputs!$B$56 | M37: S20 | N37: =HYPERLINK("https://ir.theice.com/press/news-details/2026/Intercontinental-Exchange-Reports-Strong-Full-Year-2025-Results/default.aspx","src")
A39: 6. SETTLEMENT AND CLEARING
A40: Priced on notional at the published NSCC value-into-net rate of $0.44 per $1m, i.e. 0.0044bps. This pool is structurally tiny, which is the honest answer: clearing is a utility-priced service. v6.1 showed it ~25x larger by applying a per-trade fee the cited filing does not contain.
C41: 2026 | D41: 2027 | E41: 2028 | F41: 2029 | G41: 2030 | H41: 2031 | I41: 2032 | J41: 2033 | K41: 2034 | L41: 2035
A42: Settlement and clearing revenue ($M) | C42: =C11*Inputs!$B$59/10000 | D42: =D11*Inputs!$B$59/10000 | E42: =E11*Inputs!$B$59/10000 | F42: =F11*Inputs!$B$59/10000 | G42: =G11*Inputs!$B$59/10000 | H42: =H11*Inputs!$B$59/10000 | I42: =I11*Inputs!$B$59/10000 | J42: =J11*Inputs!$B$59/10000 | ... L42: =L11*Inputs!$B$59/10000 | M42: S22 | N42: =HYPERLINK("https://www.dtcc.com/-/media/Files/Downloads/legal/fee-guides/nsccfeeguide.pdf","src")
A44: TOTAL REVENUE POOL
C45: 2026 | D45: 2027 | E45: 2028 | F45: 2029 | G45: 2030 | H45: 2031 | I45: 2032 | J45: 2033 | K45: 2034 | L45: 2035
A46: 1 Trading | C46: =C13 | D46: =D13 | E46: =E13 | F46: =F13 | G46: =G13 | H46: =H13 | I46: =I13 | J46: =J13 | ... L46: =L13
A47: 2 Securities lending | C47: =C19 | D47: =D19 | E47: =E19 | F47: =F19 | G47: =G19 | H47: =H19 | I47: =I19 | J47: =J19 | ... L47: =L19
A48: 3 Custody and prime | C48: =C25 | D48: =D25 | E48: =E25 | F48: =F25 | G48: =G25 | H48: =H25 | I48: =I25 | J48: =J25 | ... L48: =L25
A49: 4 Tokenization and servicing | C49: =C33 | D49: =D33 | E49: =E33 | F49: =F33 | G49: =G33 | H49: =H33 | I49: =I33 | J49: =J33 | ... L49: =L33
A50: 5 Market data and index | C50: =C37 | D50: =D37 | E50: =E37 | F50: =F37 | G50: =G37 | H50: =H37 | I50: =I37 | J50: =J37 | ... L50: =L37
A51: 6 Settlement and clearing | C51: =C42 | D51: =D42 | E51: =E42 | F51: =F42 | G51: =G42 | H51: =H42 | I51: =I42 | J51: =J42 | ... L51: =L42
A52: TOTAL REVENUE POOL ($M) | C52: =SUM(C46:C51) | D52: =SUM(D46:D51) | E52: =SUM(E46:E51) | F52: =SUM(F46:F51) | G52: =SUM(G46:G51) | H52: =SUM(H46:H51) | I52: =SUM(I46:I51) | J52: =SUM(J46:J51) | ... L52: =SUM(L46:L51)
A53: Total revenue pool ($Bn) | C53: =C52/1000 | D53: =D52/1000 | E53: =E52/1000 | F53: =F52/1000 | G53: =G52/1000 | H53: =H52/1000 | I53: =I52/1000 | J53: =J52/1000 | ... L53: =L52/1000
A54: Revenue yield on tokenized market cap (bps) | C54: =IFERROR(C52/C6*10000,0) | D54: =IFERROR(D52/D6*10000,0) | E54: =IFERROR(E52/E6*10000,0) | F54: =IFERROR(F52/F6*10000,0) | G54: =IFERROR(G52/G6*10000,0) | H54: =IFERROR(H52/H6*10000,0) | I54: =IFERROR(I52/I6*10000,0) | J54: =IFERROR(J52/J6*10000,0) | ... L54: =IFERROR(L52/L6*10000,0)
A56: REVENUE MIX (% OF TOTAL)
C57: 2026 | D57: 2027 | E57: 2028 | F57: 2029 | G57: 2030 | H57: 2031 | I57: 2032 | J57: 2033 | K57: 2034 | L57: 2035
A58: 1 Trading | C58: =IFERROR(C46/C52,0) | D58: =IFERROR(D46/D52,0) | E58: =IFERROR(E46/E52,0) | F58: =IFERROR(F46/F52,0) | G58: =IFERROR(G46/G52,0) | H58: =IFERROR(H46/H52,0) | I58: =IFERROR(I46/I52,0) | J58: =IFERROR(J46/J52,0) | ... L58: =IFERROR(L46/L52,0)
A59: 2 Securities lending | C59: =IFERROR(C47/C52,0) | D59: =IFERROR(D47/D52,0) | E59: =IFERROR(E47/E52,0) | F59: =IFERROR(F47/F52,0) | G59: =IFERROR(G47/G52,0) | H59: =IFERROR(H47/H52,0) | I59: =IFERROR(I47/I52,0) | J59: =IFERROR(J47/J52,0) | ... L59: =IFERROR(L47/L52,0)
A60: 3 Custody and prime | C60: =IFERROR(C48/C52,0) | D60: =IFERROR(D48/D52,0) | E60: =IFERROR(E48/E52,0) | F60: =IFERROR(F48/F52,0) | G60: =IFERROR(G48/G52,0) | H60: =IFERROR(H48/H52,0) | I60: =IFERROR(I48/I52,0) | J60: =IFERROR(J48/J52,0) | ... L60: =IFERROR(L48/L52,0)
A61: 4 Tokenization and servicing | C61: =IFERROR(C49/C52,0) | D61: =IFERROR(D49/D52,0) | E61: =IFERROR(E49/E52,0) | F61: =IFERROR(F49/F52,0) | G61: =IFERROR(G49/G52,0) | H61: =IFERROR(H49/H52,0) | I61: =IFERROR(I49/I52,0) | J61: =IFERROR(J49/J52,0) | ... L61: =IFERROR(L49/L52,0)
A62: 5 Market data and index | C62: =IFERROR(C50/C52,0) | D62: =IFERROR(D50/D52,0) | E62: =IFERROR(E50/E52,0) | F62: =IFERROR(F50/F52,0) | G62: =IFERROR(G50/G52,0) | H62: =IFERROR(H50/H52,0) | I62: =IFERROR(I50/I52,0) | J62: =IFERROR(J50/J52,0) | ... L62: =IFERROR(L50/L52,0)
A63: 6 Settlement and clearing | C63: =IFERROR(C51/C52,0) | D63: =IFERROR(D51/D52,0) | E63: =IFERROR(E51/E52,0) | F63: =IFERROR(F51/F52,0) | G63: =IFERROR(G51/G52,0) | H63: =IFERROR(H51/H52,0) | I63: =IFERROR(I51/I52,0) | J63: =IFERROR(J51/J52,0) | ... L63: =IFERROR(L51/L52,0)
A64: Check | C64: =SUM(C58:C63) | D64: =SUM(D58:D63) | E64: =SUM(E58:E63) | F64: =SUM(F58:F63) | G64: =SUM(G58:G63) | H64: =SUM(H58:H63) | I64: =SUM(I58:I63) | J64: =SUM(J58:J63) | ... L64: =SUM(L58:L63)

Sheet Scenarios
A1: Scenarios
A2: Terminal ceilings are set to sourced outcomes: the bear case is the ADR wrapper, the bull case is the domestic equity ETF wrapper.
A4: TERMINAL PENETRATION CEILINGS
B5: Bear | C5: Base | D5: Bull
A6: Russell 1000 | B6: 0.02 | C6: =Inputs!B38 | D6: 0.13
A7: Russell 2000 | B7: 0.012 | C7: =Inputs!B39 | D7: 0.08
A8: Other listed | B8: 0.005 | C8: =Inputs!B40 | D8: 0.03
A10: Anchoring | B10: ADR outcome | C10: between | D10: ETF outcome
A11: Sourced reference: DR value held / US market cap | B11: =Inputs!B37 | F11: S13 | G11: =HYPERLINK("https://www.bny.com/assets/corporate/documents/pdf/year-In-review-v8.pdf","open")
A12: Sourced reference: domestic equity ETF assets / US market cap | D12: =Inputs!B36 | F12: S10 | G12: =HYPERLINK("https://www.ici.org/research/stats/etf/etfs_04_26","open")
A14: CURVE STEEPNESS AND SOLVED INFLECTION YEAR
A15: Each scenario varies both the ceiling and the steepness, then solves its own inflection year so that every scenario curve still passes through the same observed 2026 base. A lower ceiling inflects earlier because the curve has less distance to travel - that is the arithmetic, not an error.
B16: Bear | C16: Base | D16: Bull
A17: Logistic steepness k | B17: 0.75 | C17: =Inputs!B41 | D17: 1.1
A18: Solved inflection year t0 | B18: =2026+LN(B6/Penetration!$B$7-1)/B$17 | C18: =2026+LN(C6/Penetration!$B$7-1)/C$17 | D18: =2026+LN(D6/Penetration!$B$7-1)/D$17
A20: TERMINAL YEAR 2035 - TOKENIZED MARKET CAP ($Bn)
B21: Bear | C21: Base | D21: Bull
A22: Russell 1000 | B22: =Projection!L6*(B6/(1+EXP(-B$17*(2035-B$18)))) | C22: =Projection!L6*(C6/(1+EXP(-C$17*(2035-C$18)))) | D22: =Projection!L6*(D6/(1+EXP(-D$17*(2035-D$18))))
A23: Russell 2000 | B23: =Projection!L7*(B7/(1+EXP(-B$17*(2035-B$18-Inputs!$B$42)))) | C23: =Projection!L7*(C7/(1+EXP(-C$17*(2035-C$18-Inputs!$B$42)))) | D23: =Projection!L7*(D7/(1+EXP(-D$17*(2035-D$18-Inputs!$B$42))))
A24: Other listed | B24: =Projection!L8*(B8/(1+EXP(-B$17*(2035-B$18-Inputs!$B$43)))) | C24: =Projection!L8*(C8/(1+EXP(-C$17*(2035-C$18-Inputs!$B$43)))) | D24: =Projection!L8*(D8/(1+EXP(-D$17*(2035-D$18-Inputs!$B$43))))
A25: Total tokenized market cap ($Bn) | B25: =SUM(B22:B24) | C25: =SUM(C22:C24) | D25: =SUM(D22:D24)
A26: Blended penetration of US market cap | B26: =B25/Projection!L9 | C26: =C25/Projection!L9 | D26: =D25/Projection!L9
A28: TERMINAL YEAR 2035 - REVENUE POOL ($M)
A29: Scales the base-case 2035 revenue pool by each scenario's tokenized market cap. Rate assumptions are held constant across scenarios so the sensitivity shown is penetration only.
B30: Bear | C30: Base | D30: Bull
A31: 1 Trading | B31: ='Revenue Pools'!L13*B25/Projection!L22 | C31: ='Revenue Pools'!L13*C25/Projection!L22 | D31: ='Revenue Pools'!L13*D25/Projection!L22
A32: 2 Securities lending | B32: ='Revenue Pools'!L19*B25/Projection!L22 | C32: ='Revenue Pools'!L19*C25/Projection!L22 | D32: ='Revenue Pools'!L19*D25/Projection!L22
A33: 3 Custody and prime | B33: ='Revenue Pools'!L25*B25/Projection!L22 | C33: ='Revenue Pools'!L25*C25/Projection!L22 | D33: ='Revenue Pools'!L25*D25/Projection!L22
A34: 4 Tokenization and servicing | B34: ='Revenue Pools'!L33*B25/Projection!L22 | C34: ='Revenue Pools'!L33*C25/Projection!L22 | D34: ='Revenue Pools'!L33*D25/Projection!L22
A35: 5 Market data and index | B35: ='Revenue Pools'!L37*B25/Projection!L22 | C35: ='Revenue Pools'!L37*C25/Projection!L22 | D35: ='Revenue Pools'!L37*D25/Projection!L22
A36: 6 Settlement and clearing | B36: ='Revenue Pools'!L42*B25/Projection!L22 | C36: ='Revenue Pools'!L42*C25/Projection!L22 | D36: ='Revenue Pools'!L42*D25/Projection!L22
A37: TOTAL REVENUE POOL 2035 ($M) | B37: =SUM(B31:B36) | C37: =SUM(C31:C36) | D37: =SUM(D31:D36)
A38: Total revenue pool 2035 ($Bn) | B38: =B37/1000 | C38: =C37/1000 | D38: =D37/1000

Sheet Analogues
A1: Wrapper Analogues
A2: Only figures that appear in a linked primary document. v6.1's 33-year ETF and 36-year ADR series were unsourced and have been removed, not carried forward.
A4: THE ETF WRAPPER - HIGH OUTCOME
A5: Metric | B5: Value | C5: As of | D5: Note
A6: First US ETF launched (SPY) | B6: 1993 | C6: - | D6: Defines year 0 for the adoption curve
A7: ETF total net assets | B7: 13,373 | C7: 31-Dec-25 | D7: ICI 2026 Fact Book Figure 2.1 | F7: S11 | G7: =HYPERLINK("https://icifactbook.org/pdf/2026-factbook-ch2.pdf","open")
A8: Number of ETFs | B8: 4,813 | C8: 31-Dec-25 | D8: ICI 2026 Fact Book Figure 2.1 | F8: S11 | G8: =HYPERLINK("https://icifactbook.org/pdf/2026-factbook-ch2.pdf","open")
A9: ETF total net assets | B9: 15,703 | C9: 30-Jun-26 | D9: ICI monthly ETF release | F9: S10 | G9: =HYPERLINK("https://www.ici.org/research/stats/etf/etfs_04_26","open")
A10: of which domestic equity | B10: 10,150 | C10: 30-Jun-26 | D10: The correct numerator for an equity penetration measure | F10: S10 | G10: =HYPERLINK("https://www.ici.org/research/stats/etf/etfs_04_26","open")
A11: of which bond | B11: 2,550 | C11: 30-Jun-26 | D11: Not equity. v6.1 included this in its penetration ratio | F11: S10 | G11: =HYPERLINK("https://www.ici.org/research/stats/etf/etfs_04_26","open")
A12: of which global / international equity | B12: 2,630 | C12: 30-Jun-26 | D12: Not US equity. v6.1 included this too | F12: S10 | G12: =HYPERLINK("https://www.ici.org/research/stats/etf/etfs_04_26","open")
A13: ETF net assets, YE2000 | B13: 66 | C13: 31-Dec-00 | D13: ICI 2024 Fact Book Figure 4.1 - year 8 | F13: S12 | G13: =HYPERLINK("https://icifactbook.org/pdf/2024-factbook-ch4.pdf","open")
A14: ETF net assets, YE2005 | B14: 301 | C14: 31-Dec-05 | D14: ICI 2024 Fact Book Figure 4.1 - year 13 | F14: S12 | G14: =HYPERLINK("https://icifactbook.org/pdf/2024-factbook-ch4.pdf","open")
A15: ETF net assets, YE2010 | B15: 992 | C15: 31-Dec-10 | D15: ICI 2024 Fact Book Figure 4.1 - year 18 | F15: S12 | G15: =HYPERLINK("https://icifactbook.org/pdf/2024-factbook-ch4.pdf","open")
A16: Domestic equity ETF penetration of US market cap | B16: =Inputs!B36 | C16: 30-Jun-26 | D16: 33 years after launch. On v6.1's all-ETF basis this reads 20.4%, which is not an equity penetration figure.
A17: Cross-check: ICI index domestic equity funds + ETFs / US market cap | B17: 0.19 | C17: 31-Dec-25 | D17: ICI 2026 Fact Book Figure 2.6. Includes index mutual funds as well as ETFs, so it sits above the ETF-only figure as expected | F17: S11 | G17: =HYPERLINK("https://icifactbook.org/pdf/2026-factbook-ch2.pdf","open")
A19: THE DR / ADR WRAPPER - LOW OUTCOME
A20: Metric | B20: Value | C20: As of | D20: Note
A21: DR value traded ($Bn) | B21: 6,600 | C21: FY2025 | D21: BNY DR Market Review 2025 | F21: S13 | G21: =HYPERLINK("https://www.bny.com/assets/corporate/documents/pdf/year-In-review-v8.pdf","open")
A22: DR value held ($Bn) | B22: 1,200 | C22: 31-Dec-25 | D22: of which North American investors hold $930bn | F22: S13 | G22: =HYPERLINK("https://www.bny.com/assets/corporate/documents/pdf/year-In-review-v8.pdf","open")
A23: DR programs outstanding | B23: 2,885 | C23: Q4 2025 | D23: Across all depositary banks | F23: S13 | G23: =HYPERLINK("https://www.bny.com/assets/corporate/documents/pdf/year-In-review-v8.pdf","open")
A24: DR value held / US equity market cap | B24: =Inputs!B37 | C24: 2026 | D24: 36 years after the DR market scaled. v6.1 modelled 4-11% on a fabricated series; the sourced figure is materially lower
A25: DR value traded / US equity value traded | B25: =6600/(Inputs!B8*Inputs!B10) | C25: FY2025 | D25: DR trading is global, so this overstates the US-only share. Directionally consistent with v6.1's 2-6% band
A27: THE TOKENIZED WRAPPER - WHERE IT STANDS TODAY
A28: Metric | B28: Value | C28: As of | D28: Note
A29: Tokenized equities on-chain value ($Bn) | B29: 2.8 | C29: 26-Aug-26 | D29: Token Terminal. Cross-checks to $2.5bn on rwa.xyz 13 days earlier | F29: S07 | G29: =HYPERLINK("https://www.cryptotimes.io/2026/08/27/tokenized-rwa-market-hits-44-7b-as-funds-hold-76-4-share/","open")
A30: Total tokenized RWA market ($Bn) | B30: 44.7 | C30: 26-Aug-26 | D30: Tokenized funds $34.1bn, commodities $7.7bn, stocks $2.8bn | F30: S07 | G30: =HYPERLINK("https://www.cryptotimes.io/2026/08/27/tokenized-rwa-market-hits-44-7b-as-funds-hold-76-4-share/","open")
A31: Token holders | B31: ~1.18m | C31: 13-Aug-26 | D31: rwa.xyz via Crypto Briefing | F31: S08 | G31: =HYPERLINK("https://cryptobriefing.com/tokenized-stocks-rwa-market-cap-share/","open")
A32: DTCC no-action letter | B32: 11-Dec-25 | C32: - | D32: Scoped to the Russell 1000, index ETFs and US Treasuries. Three-year term | F32: S05 | G32: =HYPERLINK("https://www.dtcc.com/news/2025/december/11/paving-the-way-to-tokenized-dtc-custodied-assets","open")
A33: DTCC platform launch | B33: Oct-2026 | C33: - | D33: July 2026 pilot, October 2026 launch | F33: S06 | G33: =HYPERLINK("https://www.coindesk.com/business/2026/05/04/wall-street-giant-dtcc-plans-tokenized-securities-platform-with-july-pilot-october-launch","open")
A34: CLARITY Act (H.R.3633) | B34: Not enacted | C34: 31-Jul-26 | D34: House passed 294-134 on 17-Jul-25; Senate Banking advanced 15-9 on 14-May-26; Senate Calendar No. 423 | F34: S27 | G34: =HYPERLINK("https://www.disruptionbanking.com/2026/07/31/clarity-act-update-where-the-crypto-market-structure-bill-stands-right-now/","open")
A36: WHAT THE EVIDENCE SAYS ABOUT SEQUENCING
A37: v6.1 assumed illiquid small caps tokenize first, on the reasoning that they gain most from 24/7 trading and fractional access. The observable evidence points the other way. The SEC's no-action letter scopes DTCC's service to the Russell 1000. Every one of the ten largest tokenized stocks - Tesla, Alphabet, Nvidia, Circle, Invesco QQQ, SPY, MicroStrategy, Apple, Coinbase, GLD - is a mega cap or an index ETF. Tokenization is following demand for global access to the names investors already want, not liquidity repair for names they do not. The model is now ordered accordingly, with the Russell 1000 leading and the other segments lagging behind fresh regulatory relief.

Sheet Audit
A1: Audit
A2: Internal consistency checks and a complete register of every forecast cell in the model.
A4: INTERNAL CONSISTENCY CHECKS
A5: Check | B5: Computed | C5: Expected | D5: Result
A6: Segment market caps sum to the SIFMA total | B6: =Inputs!B19+Inputs!B18+Inputs!B20 | C6: =Inputs!B6 | D6: =IF(ABS(B6-C6)<=ABS(C6)*0.0001+0.000001,"PASS","FAIL")
A7: Segment company counts sum to the SIFMA total | B7: =Inputs!B21+Inputs!B22+Inputs!B23 | C7: =Inputs!B7 | D7: =IF(ABS(B7-C7)<=ABS(C7)*0.0001+0.000001,"PASS","FAIL")
A8: Projection year 1 market cap equals the input market cap | B8: =Projection!C9 | C8: =Inputs!B6 | D8: =IF(ABS(B8-C8)<=ABS(C8)*0.0001+0.000001,"PASS","FAIL")
A9: Adoption curve passes through the observed 2026 base ($Bn) | B9: =Projection!C19 | C9: =Inputs!B28*Inputs!B30 | D9: =IF(ABS(B9-C9)<=ABS(C9)*0.0001+0.000001,"PASS","FAIL")
A10: Revenue mix sums to 100% in the terminal year | B10: ='Revenue Pools'!L64 | C10: =1 | D10: =IF(ABS(B10-C10)<=ABS(C10)*0.0001+0.000001,"PASS","FAIL")
A11: Revenue pool components sum to the stated total ($M) | B11: ='Revenue Pools'!L52 | C11: =SUM('Revenue Pools'!L46:L51) | D11: =IF(ABS(B11-C11)<=ABS(C11)*0.0001+0.000001,"PASS","FAIL")
A12: Base scenario terminal market cap equals the projection ($Bn) | B12: =Scenarios!C25 | C12: =Projection!L22 | D12: =IF(ABS(B12-C12)<=ABS(C12)*0.0001+0.000001,"PASS","FAIL")
A13: Base scenario terminal revenue equals the projection ($M) | B13: =Scenarios!C37 | C13: ='Revenue Pools'!L52 | D13: =IF(ABS(B13-C13)<=ABS(C13)*0.0001+0.000001,"PASS","FAIL")
A14: Implied US turnover is consistent with the ADV input | B14: =Inputs!B12 | C14: =Inputs!B8*Inputs!B10/Inputs!B11 | D14: =IF(ABS(B14-C14)<=ABS(C14)*0.0001+0.000001,"PASS","FAIL")
A15: All checks | D15: =IF(COUNTIF(D6:D14,"FAIL")=0,"ALL PASS","SEE FAILURES")
A17: OVERRIDE STATUS
A18: Penetration override cells currently in use | B18: =SUM(Penetration!C27:L27) | E18: Zero means the model is running purely on the fitted curve. Any non-zero value means a manual path has been imposed somewhere - check the Penetration tab before circulating.
A20: FORECAST REGISTER - EVERY JUDGEMENT IN THE MODEL
A21: These are the only cells in the workbook that are not either a verified figure or arithmetic on verified figures. Nothing else is assumed.
A22: Forecast input | B22: Cell | C22: Value | E22: Bracketed by these sourced reference points
A23: Terminal ceiling - Russell 1000 | B23: Inputs!B38 | C23: =Inputs!B38 | E23: Low: DR value held 1.6% of US market cap (S13). High: domestic equity ETF assets 13.2% (S10).
A24: Terminal ceiling - Russell 2000 | B24: Inputs!B39 | C24: =Inputs!B39 | E24: Same bracket, set below the Russell 1000 ceiling because the segment sits outside the DTCC no-action perimeter (S05).
A25: Terminal ceiling - other listed | B25: Inputs!B40 | C25: =Inputs!B40 | E25: Set at the DR outcome. Micro caps lack the global retail demand that drives the observed tokenized universe (S09).
A26: Logistic steepness k | B26: Inputs!B41 | C26: =Inputs!B41 | E26: Shape only. The ETF wrapper took 33 years to reach 13.2%; k=0.9 implies a materially faster curve, which the model treats as the base case because tokenization is infrastructure migration rather than a new product.
A27: Adoption lag - Russell 2000 | B27: Inputs!B42 | C27: =Inputs!B42 | E27: The current no-action letter runs three years from 11-Dec-25 and covers the Russell 1000 only (S05).
A28: Adoption lag - other listed | B28: Inputs!B43 | C28: =Inputs!B43 | E28: Two further relief cycles beyond the Russell 2000.
A29: Equity market cap growth p.a. | B29: Inputs!B44 | C29: =Inputs!B44 | E29: Long-run nominal. Applied uniformly, so it cancels out of every penetration ratio and affects only absolute dollar levels.
A30: Crypto-venue share of volume, 2026 / 2035 | B30: Inputs!B67:C67 | C30: =Inputs!B67 | E30: Blends Coinbase institutional spot at 8.6bps (S16) with Robinhood retail equity at 1.3bps (S17). Both endpoints are disclosed; only the weighting is judged.
A31: Tokenized turnover vs US turnover, 2026 / 2035 | B31: Inputs!B68:C68 | C31: =Inputs!B68 | E31: Applied to the derived 4.0x US turnover (S03, S28). Converges to parity by 2035.
A32: Lendable share of tokenized cap, 2026 / 2035 | B32: Inputs!B69:C69 | C32: =Inputs!B69 | E32: Utilisation itself is not judged - it is the disclosed 6.96% from S&P Global (S14).
A33: Institutional custody share, 2026 / 2035 | B33: Inputs!B70:C70 | C33: =Inputs!B70 | E33: The fee rate is not judged - it is BNY's disclosed 1.72bps (S19).
A34: Digital custody premium over BNY rate | B34: Inputs!B71:C71 | C34: =Inputs!B71 | E34: Coinbase folded custodial fee revenue into Other subscription revenue from Q1'25, so a digital-native custody rate is no longer derivable from public disclosure (S16). This premium is the honest placeholder for that gap.
A35: Tokenization + servicing yield, 2026 / 2035 | B35: Inputs!B72:C72 | C35: =Inputs!B72 | E35: Bracketed by DTCC's 0.066bps utility servicing yield on listed securities (S31, S32) and Securitize's 134bps full-service fund tokenization yield (S24). Set near the low end because the wrapper is incremental to servicing that already happens, and because no tokenized equity platform publishes an explicit servicing fee (S33).
A36: Share of observed base in Russell 1000 | B36: Inputs!B30 | C36: =Inputs!B30 | E36: Near-verified: all ten largest tokenized stocks are Russell 1000 constituents or index ETFs (S09). Set to 100% because no material tokenized small cap has been identified.
A38: KNOWN LIMITATIONS - STATED RATHER THAN BURIED
A39: - Segment market caps are struck on two dates. SIFMA's $76.9T is at 30-Jun-26; the Russell figures are at the 30-Apr-26 rank day. The residual 'other listed' segment absorbs the 61-day gap, so its $1.3T is the least precise figure in the model.
A40: - Securitize is a fund-tokenization business, not an equity-tokenization business. Its disclosed yield is the closest public comparable for pool 4 but the asset mix differs. No public company yet discloses equity-tokenization revenue against equity-tokenization AUM.
A41: - The securities lending utilisation of 6.96% is a global all-asset-class figure. A US-equity-specific utilisation is not published free of charge; if you have S&P Global terminal access, the Americas equity line in the monthly Securities Finance snapshot is the figure to substitute.
A42: - The revenue pools are gross ecosystem pools, not any single firm's revenue. v6.1 applied a platform-share haircut to securities lending only, which made that pool non-comparable with the other five. The haircut has been removed rather than extended.
A43: - Trading and settlement revenue both scale with the same volume figure, so they are correlated by construction. They are not double-counting - one is a fee on execution, the other a fee on clearing - but they will move together under any volume shock.
A44: - The 2026 anchor is a point-in-time reading of a market that moves fast. Tokenized equity value roughly doubled over the twelve months to August 2026. Re-strike the anchor on Inputs before using the model in a note.
A45: - The terminal revenue yield of roughly 28bps on tokenized market cap is well above what the traditional US equity ecosystem earns. It is driven almost entirely by one judgement: that 30% of tokenized volume still prices on crypto-venue terms (8.6bps) rather than retail equity terms (1.3bps) in 2035. If that share goes to zero the trading pool halves. This is the single most sensitive input in the revenue build - test it before quoting a number.
A47: UPDATE LOG - 10-Sep-2026
A48: 1. | B48: S01 SIFMA 2Q26 re-opened and confirmed verbatim: market cap $76.9T, 5,532 listed companies. The +16.5% Q/Q move is SIFMA's own figure, not an error.
A49: 2. | B49: S04 LSEG Russell reconstitution re-opened and confirmed verbatim: Russell 3000 $75.6T on the 30-Apr-2026 rank day, Russell 2000 $3.5T, breakpoint $5.7bn.
A50: 3. | B50: S10 S&P Global securities lending re-opened and confirmed verbatim: revenue $14.9bn, equities $11.5bn, lendable $46.7T, on-loan $3.25T.
A51: 4. | B51: S10 ICI refreshed from June to July 2026: domestic equity ETFs $10,090.4bn (was $10.15T), total ETFs $15.67T, 5,182 funds. Inputs B36 updated.
A52: 5. | B52: S22 NSCC fee guide now reads 0.46 on retrieval. The 0.44 rate is evidenced by SR-NSCC-2025-017 (S23), effective 01-Jan-2026. Inputs row 58 repointed to S23.
A53: 6. | B53: S06 replaced: CoinDesk secondary swapped for the DTCC primary release of 15-Jul-2026, which also carries the 100+ working group figure.
A54: 7. | B54: S34, S35, S36 added: DTCC live production trades page, Corp Fin Statement on Tokenized Securities, and the Nasdaq tokenized trading approval order.
A55: 8. | B55: Not refreshable at 10-Sep-2026: SIFMA 3Q26 and Securitize Q3'26 are not yet published; the quarter had not closed.
